// class version 51.0 (51)
// access flags 0x21
public class edu/utd/sonnv/Test implements edu/columbia/cs/psl/phosphor/struct/TaintedWithObjTag  {


  @Ledu/columbia/cs/psl/phosphor/runtime/TaintInstrumented;() // invisible
  // compiled from: Test.java
  // access flags 0x8
  static INNERCLASS edu/utd/sonnv/Test$TestX edu/utd/sonnv/Test TestX

  // access flags 0x1
  public <init>()V
   L0
   L1
   L2
   L3
    LINENUMBER 3 L3
    ALOAD 0
    INVOKESPECIAL java/lang/Object.<init> ()V
    GETSTATIC java/lang/System.out : Ljava/io/PrintStream;
    LDC "Void: edu.utd.sonnv.Test.<init>"
    INVOKEVIRTUAL java/io/PrintStream.println (Ljava/lang/String;)V
    RETURN
   L4
    LOCALVARIABLE this Ledu/utd/sonnv/Test; L3 L4 0
   L5
    MAXSTACK = 102
    MAXLOCALS = 1

  // access flags 0x1
  public test5$$PHOSPHORTAGGED(Ledu/columbia/cs/psl/phosphor/runtime/Taint;I)Ljava/lang/String;
   L0
   L1
   L2
    NEW edu/columbia/cs/psl/phosphor/struct/TaintedIntWithObjTag
    DUP
    INVOKESPECIAL edu/columbia/cs/psl/phosphor/struct/TaintedIntWithObjTag.<init> ()V
    ASTORE 3
   L3
    ALOAD 1
    ILOAD 2
    ACONST_NULL
    ALOAD 3
    INVOKESTATIC edu/columbia/cs/psl/phosphor/runtime/MultiTainter.taintedInt$$PHOSPHORTAGGED (Ledu/columbia/cs/psl/phosphor/runtime/Taint;ILjava/lang/Object;Ledu/columbia/cs/psl/phosphor/struct/TaintedIntWithObjTag;)Ledu/columbia/cs/psl/phosphor/struct/TaintedIntWithObjTag;
    DUP
    GETFIELD edu/columbia/cs/psl/phosphor/struct/TaintedIntWithObjTag.taint : Ledu/columbia/cs/psl/phosphor/runtime/Taint;
    SWAP
    GETFIELD edu/columbia/cs/psl/phosphor/struct/TaintedIntWithObjTag.val : I
    ISTORE 2
    INVOKESTATIC edu/columbia/cs/psl/phosphor/runtime/Taint.copyTaint (Ledu/columbia/cs/psl/phosphor/runtime/Taint;)Ledu/columbia/cs/psl/phosphor/runtime/Taint;
    ASTORE 1
   L4
    LINENUMBER 5 L4
    ILOAD 2
    IFNE L5
   L6
   L7
    LINENUMBER 6 L7
    ACONST_NULL
    ARETURN
   L5
    LINENUMBER 8 L5
   FRAME FULL [edu/utd/sonnv/Test edu/columbia/cs/psl/phosphor/runtime/Taint I edu/columbia/cs/psl/phosphor/struct/TaintedIntWithObjTag] []
    ILOAD 2
    ICONST_1
    IF_ICMPNE L8
   L9
   L10
    LINENUMBER 9 L10
    ALOAD 0
    ALOAD 0
   L11
    NEW java/lang/StringBuilder
    DUP
    INVOKESPECIAL java/lang/StringBuilder.<init> ()V
    ALOAD 1
    ILOAD 2
    INVOKEVIRTUAL java/lang/StringBuilder.append$$PHOSPHORTAGGED (Ledu/columbia/cs/psl/phosphor/runtime/Taint;I)Ljava/lang/StringBuilder;
    LDC ""
    INVOKEVIRTUAL java/lang/StringBuilder.append (Ljava/lang/String;)Ljava/lang/StringBuilder;
    INVOKEVIRTUAL java/lang/StringBuilder.toString ()Ljava/lang/String;
    INVOKEVIRTUAL edu/utd/sonnv/Test.testTernaryWithObject (Ljava/lang/String;)Ljava/lang/String;
    INVOKEVIRTUAL edu/utd/sonnv/Test.test6 (Ljava/lang/String;)Ljava/lang/String;
    ASTORE 2
    ALOAD 2
   L12
    NEW edu/columbia/cs/psl/phosphor/runtime/Taint
    DUP
    LDC "edu.utd.sonnv.Test.test5"
    INVOKESPECIAL edu/columbia/cs/psl/phosphor/runtime/Taint.<init> (Ljava/lang/Object;)V
    INVOKESTATIC edu/columbia/cs/psl/phosphor/runtime/MultiTainter.taintedObject (Ljava/lang/Object;Ledu/columbia/cs/psl/phosphor/runtime/Taint;)V
    ALOAD 2
    GETSTATIC java/lang/System.out : Ljava/io/PrintStream;
    LDC "Return object: edu.utd.sonnv.Test.test5"
    INVOKEVIRTUAL java/io/PrintStream.println (Ljava/lang/String;)V
    ARETURN
   L8
    LINENUMBER 11 L8
   FRAME FULL [edu/utd/sonnv/Test edu/columbia/cs/psl/phosphor/runtime/Taint I edu/columbia/cs/psl/phosphor/struct/TaintedIntWithObjTag] []
    ALOAD 0
   L13
    NEW java/lang/StringBuilder
    DUP
    INVOKESPECIAL java/lang/StringBuilder.<init> ()V
    LDC "Hello"
    INVOKEVIRTUAL java/lang/StringBuilder.append (Ljava/lang/String;)Ljava/lang/StringBuilder;
    ALOAD 1
    ILOAD 2
    INVOKEVIRTUAL java/lang/StringBuilder.append$$PHOSPHORTAGGED (Ledu/columbia/cs/psl/phosphor/runtime/Taint;I)Ljava/lang/StringBuilder;
    INVOKEVIRTUAL java/lang/StringBuilder.toString ()Ljava/lang/String;
    INVOKEVIRTUAL edu/utd/sonnv/Test.test6 (Ljava/lang/String;)Ljava/lang/String;
    ASTORE 2
    ALOAD 2
   L14
    NEW edu/columbia/cs/psl/phosphor/runtime/Taint
    DUP
    LDC "edu.utd.sonnv.Test.test5"
    INVOKESPECIAL edu/columbia/cs/psl/phosphor/runtime/Taint.<init> (Ljava/lang/Object;)V
    INVOKESTATIC edu/columbia/cs/psl/phosphor/runtime/MultiTainter.taintedObject (Ljava/lang/Object;Ledu/columbia/cs/psl/phosphor/runtime/Taint;)V
    ALOAD 2
    GETSTATIC java/lang/System.out : Ljava/io/PrintStream;
    LDC "Return object: edu.utd.sonnv.Test.test5"
    INVOKEVIRTUAL java/io/PrintStream.println (Ljava/lang/String;)V
    ARETURN
   L15
    LOCALVARIABLE this Ledu/utd/sonnv/Test; L4 L15 0
   L16
    LOCALVARIABLE phosphorReturnPreAlloc0 Ledu/columbia/cs/psl/phosphor/struct/TaintedIntWithObjTag; L2 L16 3
    LOCALVARIABLE x_TAINT Ledu/columbia/cs/psl/phosphor/runtime/Taint; L4 L15 1
    LOCALVARIABLE x I L4 L15 2
    MAXSTACK = 104
    MAXLOCALS = 4

  // access flags 0x1
  public test6(Ljava/lang/String;)Ljava/lang/String;
   L0
   L1
   L2
   L3
    LINENUMBER 15 L3
    NEW java/lang/StringBuilder
    DUP
    INVOKESPECIAL java/lang/StringBuilder.<init> ()V
    LDC "Hello"
    INVOKEVIRTUAL java/lang/StringBuilder.append (Ljava/lang/String;)Ljava/lang/StringBuilder;
    ALOAD 1
    INVOKEVIRTUAL java/lang/StringBuilder.append (Ljava/lang/String;)Ljava/lang/StringBuilder;
    INVOKEVIRTUAL java/lang/StringBuilder.toString ()Ljava/lang/String;
    ASTORE 2
   L4
    LINENUMBER 16 L4
    ALOAD 2
   L5
    NEW edu/columbia/cs/psl/phosphor/runtime/Taint
    DUP
    LDC "edu.utd.sonnv.Test.test6"
    INVOKESPECIAL edu/columbia/cs/psl/phosphor/runtime/Taint.<init> (Ljava/lang/Object;)V
    INVOKESTATIC edu/columbia/cs/psl/phosphor/runtime/MultiTainter.taintedObject (Ljava/lang/Object;Ledu/columbia/cs/psl/phosphor/runtime/Taint;)V
    ALOAD 2
    GETSTATIC java/lang/System.out : Ljava/io/PrintStream;
    LDC "Return object: edu.utd.sonnv.Test.test6"
    INVOKEVIRTUAL java/io/PrintStream.println (Ljava/lang/String;)V
    ARETURN
   L6
    LOCALVARIABLE this Ledu/utd/sonnv/Test; L3 L6 0
    LOCALVARIABLE x Ljava/lang/String; L3 L6 1
    LOCALVARIABLE result Ljava/lang/String; L4 L6 2
   L7
    MAXSTACK = 104
    MAXLOCALS = 3

  // access flags 0x1
  public testTernaryWithObject(Ljava/lang/String;)Ljava/lang/String;
   L0
   L1
   L2
   L3
    LINENUMBER 20 L3
    ACONST_NULL
    ASTORE 2
   L4
    LINENUMBER 21 L4
    ALOAD 1
    IFNONNULL L5
   L6
    LDC ""
    GOTO L7
   L8
   L5
   FRAME FULL [edu/utd/sonnv/Test java/lang/String N] []
    ALOAD 0
    ALOAD 2
    INVOKEVIRTUAL edu/utd/sonnv/Test.test6 (Ljava/lang/String;)Ljava/lang/String;
   L7
   FRAME FULL [edu/utd/sonnv/Test java/lang/String N] [java/lang/String]
    ASTORE 3
    ALOAD 3
   L9
    NEW edu/columbia/cs/psl/phosphor/runtime/Taint
    DUP
    LDC "edu.utd.sonnv.Test.testTernaryWithObject"
    INVOKESPECIAL edu/columbia/cs/psl/phosphor/runtime/Taint.<init> (Ljava/lang/Object;)V
    INVOKESTATIC edu/columbia/cs/psl/phosphor/runtime/MultiTainter.taintedObject (Ljava/lang/Object;Ledu/columbia/cs/psl/phosphor/runtime/Taint;)V
    ALOAD 3
    GETSTATIC java/lang/System.out : Ljava/io/PrintStream;
    LDC "Return object: edu.utd.sonnv.Test.testTernaryWithObject"
    INVOKEVIRTUAL java/io/PrintStream.println (Ljava/lang/String;)V
    ARETURN
   L10
    LOCALVARIABLE this Ledu/utd/sonnv/Test; L3 L10 0
    LOCALVARIABLE x Ljava/lang/String; L3 L10 1
    LOCALVARIABLE result Ljava/lang/String; L4 L10 2
   L11
    MAXSTACK = 104
    MAXLOCALS = 4

  // access flags 0x1
  public testObj1$$PHOSPHORTAGGED(Ledu/columbia/cs/psl/phosphor/runtime/Taint;I)Ljava/lang/String;
   L0
   L1
   L2
    NEW edu/columbia/cs/psl/phosphor/struct/TaintedIntWithObjTag
    DUP
    INVOKESPECIAL edu/columbia/cs/psl/phosphor/struct/TaintedIntWithObjTag.<init> ()V
    ASTORE 3
   L3
    ALOAD 1
    ILOAD 2
    ACONST_NULL
    ALOAD 3
    INVOKESTATIC edu/columbia/cs/psl/phosphor/runtime/MultiTainter.taintedInt$$PHOSPHORTAGGED (Ledu/columbia/cs/psl/phosphor/runtime/Taint;ILjava/lang/Object;Ledu/columbia/cs/psl/phosphor/struct/TaintedIntWithObjTag;)Ledu/columbia/cs/psl/phosphor/struct/TaintedIntWithObjTag;
    DUP
    GETFIELD edu/columbia/cs/psl/phosphor/struct/TaintedIntWithObjTag.taint : Ledu/columbia/cs/psl/phosphor/runtime/Taint;
    SWAP
    GETFIELD edu/columbia/cs/psl/phosphor/struct/TaintedIntWithObjTag.val : I
    ISTORE 2
    INVOKESTATIC edu/columbia/cs/psl/phosphor/runtime/Taint.copyTaint (Ledu/columbia/cs/psl/phosphor/runtime/Taint;)Ledu/columbia/cs/psl/phosphor/runtime/Taint;
    ASTORE 1
   L4
    LINENUMBER 25 L4
    ALOAD 0
    ALOAD 1
    ILOAD 2
    ALOAD 3
    INVOKEVIRTUAL edu/utd/sonnv/Test.getCastingValue$$PHOSPHORTAGGED (Ledu/columbia/cs/psl/phosphor/runtime/Taint;ILedu/columbia/cs/psl/phosphor/struct/TaintedIntWithObjTag;)Ledu/columbia/cs/psl/phosphor/struct/TaintedIntWithObjTag;
    GETFIELD edu/columbia/cs/psl/phosphor/struct/TaintedIntWithObjTag.val : I
    ISTORE 4
   L5
    LINENUMBER 26 L5
    ALOAD 0
    ACONST_NULL
    ICONST_2
    INVOKEVIRTUAL edu/utd/sonnv/Test.testSwitchCase$$PHOSPHORTAGGED (Ledu/columbia/cs/psl/phosphor/runtime/Taint;I)Ljava/lang/String;
    ASTORE 2
    ALOAD 2
   L6
    NEW edu/columbia/cs/psl/phosphor/runtime/Taint
    DUP
    LDC "edu.utd.sonnv.Test.testObj1"
    INVOKESPECIAL edu/columbia/cs/psl/phosphor/runtime/Taint.<init> (Ljava/lang/Object;)V
    INVOKESTATIC edu/columbia/cs/psl/phosphor/runtime/MultiTainter.taintedObject (Ljava/lang/Object;Ledu/columbia/cs/psl/phosphor/runtime/Taint;)V
    ALOAD 2
    GETSTATIC java/lang/System.out : Ljava/io/PrintStream;
    LDC "Return object: edu.utd.sonnv.Test.testObj1"
    INVOKEVIRTUAL java/io/PrintStream.println (Ljava/lang/String;)V
    ARETURN
   L7
    LOCALVARIABLE this Ledu/utd/sonnv/Test; L4 L7 0
   L8
    LOCALVARIABLE phosphorReturnPreAlloc0 Ledu/columbia/cs/psl/phosphor/struct/TaintedIntWithObjTag; L2 L8 3
    LOCALVARIABLE x_TAINT Ledu/columbia/cs/psl/phosphor/runtime/Taint; L4 L7 1
    LOCALVARIABLE x I L4 L7 2
    LOCALVARIABLE y I L5 L7 4
    MAXSTACK = 104
    MAXLOCALS = 5

  // access flags 0x1
  public testSwitchCase$$PHOSPHORTAGGED(Ledu/columbia/cs/psl/phosphor/runtime/Taint;I)Ljava/lang/String;
   L0
   L1
   L2
    NEW edu/columbia/cs/psl/phosphor/struct/TaintedIntWithObjTag
    DUP
    INVOKESPECIAL edu/columbia/cs/psl/phosphor/struct/TaintedIntWithObjTag.<init> ()V
    ASTORE 3
   L3
    ALOAD 1
    ILOAD 2
    ACONST_NULL
    ALOAD 3
    INVOKESTATIC edu/columbia/cs/psl/phosphor/runtime/MultiTainter.taintedInt$$PHOSPHORTAGGED (Ledu/columbia/cs/psl/phosphor/runtime/Taint;ILjava/lang/Object;Ledu/columbia/cs/psl/phosphor/struct/TaintedIntWithObjTag;)Ledu/columbia/cs/psl/phosphor/struct/TaintedIntWithObjTag;
    DUP
    GETFIELD edu/columbia/cs/psl/phosphor/struct/TaintedIntWithObjTag.taint : Ledu/columbia/cs/psl/phosphor/runtime/Taint;
    SWAP
    GETFIELD edu/columbia/cs/psl/phosphor/struct/TaintedIntWithObjTag.val : I
    ISTORE 2
    INVOKESTATIC edu/columbia/cs/psl/phosphor/runtime/Taint.copyTaint (Ledu/columbia/cs/psl/phosphor/runtime/Taint;)Ledu/columbia/cs/psl/phosphor/runtime/Taint;
    ASTORE 1
   L4
    LINENUMBER 30 L4
    ACONST_NULL
    ICONST_1
   L5
    ISTORE 4
    INVOKESTATIC edu/columbia/cs/psl/phosphor/runtime/Taint.copyTaint (Ledu/columbia/cs/psl/phosphor/runtime/Taint;)Ledu/columbia/cs/psl/phosphor/runtime/Taint;
    ASTORE 5
   L6
    LINENUMBER 31 L6
    ILOAD 2
    LOOKUPSWITCH
      1: L7
      2: L8
      default: L9
   L7
    LINENUMBER 33 L7
   FRAME FULL [edu/utd/sonnv/Test edu/columbia/cs/psl/phosphor/runtime/Taint I edu/columbia/cs/psl/phosphor/struct/TaintedIntWithObjTag I edu/columbia/cs/psl/phosphor/runtime/Taint] []
    ALOAD 0
    ALOAD 1
    ILOAD 2
    ALOAD 3
    INVOKEVIRTUAL edu/utd/sonnv/Test.getReturnPrimitiveConst$$PHOSPHORTAGGED (Ledu/columbia/cs/psl/phosphor/runtime/Taint;ILedu/columbia/cs/psl/phosphor/struct/TaintedIntWithObjTag;)Ledu/columbia/cs/psl/phosphor/struct/TaintedIntWithObjTag;
    DUP
    GETFIELD edu/columbia/cs/psl/phosphor/struct/TaintedIntWithObjTag.taint : Ledu/columbia/cs/psl/phosphor/runtime/Taint;
    SWAP
    GETFIELD edu/columbia/cs/psl/phosphor/struct/TaintedIntWithObjTag.val : I
   L10
    ISTORE 4
    INVOKESTATIC edu/columbia/cs/psl/phosphor/runtime/Taint.copyTaint (Ledu/columbia/cs/psl/phosphor/runtime/Taint;)Ledu/columbia/cs/psl/phosphor/runtime/Taint;
    ASTORE 5
   L11
    LINENUMBER 34 L11
    ALOAD 0
    ALOAD 5
    ILOAD 4
    INVOKEVIRTUAL edu/utd/sonnv/Test.test5$$PHOSPHORTAGGED (Ledu/columbia/cs/psl/phosphor/runtime/Taint;I)Ljava/lang/String;
    ASTORE 2
    ALOAD 2
   L12
    NEW edu/columbia/cs/psl/phosphor/runtime/Taint
    DUP
    LDC "edu.utd.sonnv.Test.testSwitchCase"
    INVOKESPECIAL edu/columbia/cs/psl/phosphor/runtime/Taint.<init> (Ljava/lang/Object;)V
    INVOKESTATIC edu/columbia/cs/psl/phosphor/runtime/MultiTainter.taintedObject (Ljava/lang/Object;Ledu/columbia/cs/psl/phosphor/runtime/Taint;)V
    ALOAD 2
    GETSTATIC java/lang/System.out : Ljava/io/PrintStream;
    LDC "Return object: edu.utd.sonnv.Test.testSwitchCase"
    INVOKEVIRTUAL java/io/PrintStream.println (Ljava/lang/String;)V
    ARETURN
   L8
    LINENUMBER 36 L8
   FRAME FULL [edu/utd/sonnv/Test edu/columbia/cs/psl/phosphor/runtime/Taint I edu/columbia/cs/psl/phosphor/struct/TaintedIntWithObjTag I edu/columbia/cs/psl/phosphor/runtime/Taint] []
    ALOAD 0
    ALOAD 1
    ILOAD 2
    ALOAD 3
    INVOKEVIRTUAL edu/utd/sonnv/Test.getCastingValue$$PHOSPHORTAGGED (Ledu/columbia/cs/psl/phosphor/runtime/Taint;ILedu/columbia/cs/psl/phosphor/struct/TaintedIntWithObjTag;)Ledu/columbia/cs/psl/phosphor/struct/TaintedIntWithObjTag;
    DUP
    GETFIELD edu/columbia/cs/psl/phosphor/struct/TaintedIntWithObjTag.taint : Ledu/columbia/cs/psl/phosphor/runtime/Taint;
    SWAP
    GETFIELD edu/columbia/cs/psl/phosphor/struct/TaintedIntWithObjTag.val : I
    ACONST_NULL
    ICONST_2
   L13
    ISTORE 6
    SWAP
    ILOAD 6
   L14
    IADD
    DUP_X2
    POP
    INVOKESTATIC edu/columbia/cs/psl/phosphor/runtime/Taint.combineTags (Ledu/columbia/cs/psl/phosphor/runtime/Taint;Ledu/columbia/cs/psl/phosphor/runtime/Taint;)Ledu/columbia/cs/psl/phosphor/runtime/Taint;
    SWAP
    ISTORE 4
    INVOKESTATIC edu/columbia/cs/psl/phosphor/runtime/Taint.copyTaint (Ledu/columbia/cs/psl/phosphor/runtime/Taint;)Ledu/columbia/cs/psl/phosphor/runtime/Taint;
    ASTORE 5
   L15
    LINENUMBER 37 L15
    ALOAD 0
    ALOAD 5
    ILOAD 4
    INVOKEVIRTUAL edu/utd/sonnv/Test.test5$$PHOSPHORTAGGED (Ledu/columbia/cs/psl/phosphor/runtime/Taint;I)Ljava/lang/String;
    ASTORE 2
    ALOAD 2
   L16
    NEW edu/columbia/cs/psl/phosphor/runtime/Taint
    DUP
    LDC "edu.utd.sonnv.Test.testSwitchCase"
    INVOKESPECIAL edu/columbia/cs/psl/phosphor/runtime/Taint.<init> (Ljava/lang/Object;)V
    INVOKESTATIC edu/columbia/cs/psl/phosphor/runtime/MultiTainter.taintedObject (Ljava/lang/Object;Ledu/columbia/cs/psl/phosphor/runtime/Taint;)V
    ALOAD 2
    GETSTATIC java/lang/System.out : Ljava/io/PrintStream;
    LDC "Return object: edu.utd.sonnv.Test.testSwitchCase"
    INVOKEVIRTUAL java/io/PrintStream.println (Ljava/lang/String;)V
    ARETURN
   L9
    LINENUMBER 42 L9
   FRAME FULL [edu/utd/sonnv/Test edu/columbia/cs/psl/phosphor/runtime/Taint I edu/columbia/cs/psl/phosphor/struct/TaintedIntWithObjTag I edu/columbia/cs/psl/phosphor/runtime/Taint] []
    ALOAD 0
   L17
    NEW java/lang/StringBuilder
    DUP
    INVOKESPECIAL java/lang/StringBuilder.<init> ()V
    ALOAD 5
    ILOAD 4
    INVOKEVIRTUAL java/lang/StringBuilder.append$$PHOSPHORTAGGED (Ledu/columbia/cs/psl/phosphor/runtime/Taint;I)Ljava/lang/StringBuilder;
    LDC ""
    INVOKEVIRTUAL java/lang/StringBuilder.append (Ljava/lang/String;)Ljava/lang/StringBuilder;
    INVOKEVIRTUAL java/lang/StringBuilder.toString ()Ljava/lang/String;
    INVOKEVIRTUAL edu/utd/sonnv/Test.test6 (Ljava/lang/String;)Ljava/lang/String;
    ASTORE 2
    ALOAD 2
   L18
    NEW edu/columbia/cs/psl/phosphor/runtime/Taint
    DUP
    LDC "edu.utd.sonnv.Test.testSwitchCase"
    INVOKESPECIAL edu/columbia/cs/psl/phosphor/runtime/Taint.<init> (Ljava/lang/Object;)V
    INVOKESTATIC edu/columbia/cs/psl/phosphor/runtime/MultiTainter.taintedObject (Ljava/lang/Object;Ledu/columbia/cs/psl/phosphor/runtime/Taint;)V
    ALOAD 2
    GETSTATIC java/lang/System.out : Ljava/io/PrintStream;
    LDC "Return object: edu.utd.sonnv.Test.testSwitchCase"
    INVOKEVIRTUAL java/io/PrintStream.println (Ljava/lang/String;)V
    ARETURN
   L19
    LOCALVARIABLE this Ledu/utd/sonnv/Test; L4 L19 0
   L20
    LOCALVARIABLE phosphorReturnPreAlloc0 Ledu/columbia/cs/psl/phosphor/struct/TaintedIntWithObjTag; L2 L20 3
    LOCALVARIABLE phosphorShadowLV2 Ledu/columbia/cs/psl/phosphor/runtime/Taint; L10 L20 5
    LOCALVARIABLE phosphorShadowLV3 I L13 L14 6
    LOCALVARIABLE phosphorShadowLVFor4XX1 Ledu/columbia/cs/psl/phosphor/runtime/Taint; L5 L10 5
    LOCALVARIABLE x_TAINT Ledu/columbia/cs/psl/phosphor/runtime/Taint; L4 L19 1
    LOCALVARIABLE x I L4 L19 2
    LOCALVARIABLE y I L6 L19 4
    MAXSTACK = 104
    MAXLOCALS = 7

  // access flags 0x1
  public testCustomizedObject()Ledu/utd/sonnv/Test$TestX;
   L0
   L1
   L2
    NEW edu/columbia/cs/psl/phosphor/struct/TaintedIntWithObjTag
    DUP
    INVOKESPECIAL edu/columbia/cs/psl/phosphor/struct/TaintedIntWithObjTag.<init> ()V
    ASTORE 1
   L3
   L4
    LINENUMBER 46 L4
    NEW edu/utd/sonnv/Test$TestX
    DUP
    INVOKESPECIAL edu/utd/sonnv/Test$TestX.<init> ()V
    ASTORE 2
   L5
    LINENUMBER 49 L5
    ALOAD 2
    ALOAD 0
    ACONST_NULL
    ICONST_3
    ACONST_NULL
    ICONST_4
    ALOAD 1
    INVOKEVIRTUAL edu/utd/sonnv/Test.testNomalCase$$PHOSPHORTAGGED (Ledu/columbia/cs/psl/phosphor/runtime/Taint;ILedu/columbia/cs/psl/phosphor/runtime/Taint;ILedu/columbia/cs/psl/phosphor/struct/TaintedIntWithObjTag;)Ledu/columbia/cs/psl/phosphor/struct/TaintedIntWithObjTag;
    DUP
    GETFIELD edu/columbia/cs/psl/phosphor/struct/TaintedIntWithObjTag.taint : Ledu/columbia/cs/psl/phosphor/runtime/Taint;
    SWAP
    GETFIELD edu/columbia/cs/psl/phosphor/struct/TaintedIntWithObjTag.val : I
    INVOKEVIRTUAL edu/utd/sonnv/Test$TestX.setF1$$PHOSPHORTAGGED (Ledu/columbia/cs/psl/phosphor/runtime/Taint;I)V
   L6
    LINENUMBER 50 L6
    ALOAD 2
   L7
    NEW edu/columbia/cs/psl/phosphor/runtime/Taint
    DUP
    LDC "edu.utd.sonnv.Test.testCustomizedObject"
    INVOKESPECIAL edu/columbia/cs/psl/phosphor/runtime/Taint.<init> (Ljava/lang/Object;)V
    INVOKESTATIC edu/columbia/cs/psl/phosphor/runtime/MultiTainter.taintedObject (Ljava/lang/Object;Ledu/columbia/cs/psl/phosphor/runtime/Taint;)V
    ALOAD 2
    GETSTATIC java/lang/System.out : Ljava/io/PrintStream;
    LDC "Return object: edu.utd.sonnv.Test.testCustomizedObject"
    INVOKEVIRTUAL java/io/PrintStream.println (Ljava/lang/String;)V
    ARETURN
   L8
    LOCALVARIABLE this Ledu/utd/sonnv/Test; L4 L8 0
   L9
    LOCALVARIABLE phosphorReturnPreAlloc0 Ledu/columbia/cs/psl/phosphor/struct/TaintedIntWithObjTag; L2 L9 1
    LOCALVARIABLE result Ledu/utd/sonnv/Test$TestX; L5 L8 2
    MAXSTACK = 104
    MAXLOCALS = 3

  // access flags 0x1
  public testNomalCase$$PHOSPHORTAGGED(Ledu/columbia/cs/psl/phosphor/runtime/Taint;ILedu/columbia/cs/psl/phosphor/runtime/Taint;ILedu/columbia/cs/psl/phosphor/struct/TaintedIntWithObjTag;)Ledu/columbia/cs/psl/phosphor/struct/TaintedIntWithObjTag;
   L0
   L1
   L2
    ALOAD 1
    ILOAD 2
    ACONST_NULL
    ALOAD 5
    INVOKESTATIC edu/columbia/cs/psl/phosphor/runtime/MultiTainter.taintedInt$$PHOSPHORTAGGED (Ledu/columbia/cs/psl/phosphor/runtime/Taint;ILjava/lang/Object;Ledu/columbia/cs/psl/phosphor/struct/TaintedIntWithObjTag;)Ledu/columbia/cs/psl/phosphor/struct/TaintedIntWithObjTag;
    DUP
    GETFIELD edu/columbia/cs/psl/phosphor/struct/TaintedIntWithObjTag.taint : Ledu/columbia/cs/psl/phosphor/runtime/Taint;
    SWAP
    GETFIELD edu/columbia/cs/psl/phosphor/struct/TaintedIntWithObjTag.val : I
    ISTORE 2
    INVOKESTATIC edu/columbia/cs/psl/phosphor/runtime/Taint.copyTaint (Ledu/columbia/cs/psl/phosphor/runtime/Taint;)Ledu/columbia/cs/psl/phosphor/runtime/Taint;
    ASTORE 1
    ALOAD 3
    ILOAD 4
    ACONST_NULL
    ALOAD 5
    INVOKESTATIC edu/columbia/cs/psl/phosphor/runtime/MultiTainter.taintedInt$$PHOSPHORTAGGED (Ledu/columbia/cs/psl/phosphor/runtime/Taint;ILjava/lang/Object;Ledu/columbia/cs/psl/phosphor/struct/TaintedIntWithObjTag;)Ledu/columbia/cs/psl/phosphor/struct/TaintedIntWithObjTag;
    DUP
    GETFIELD edu/columbia/cs/psl/phosphor/struct/TaintedIntWithObjTag.taint : Ledu/columbia/cs/psl/phosphor/runtime/Taint;
    SWAP
    GETFIELD edu/columbia/cs/psl/phosphor/struct/TaintedIntWithObjTag.val : I
    ISTORE 4
    INVOKESTATIC edu/columbia/cs/psl/phosphor/runtime/Taint.copyTaint (Ledu/columbia/cs/psl/phosphor/runtime/Taint;)Ledu/columbia/cs/psl/phosphor/runtime/Taint;
    ASTORE 3
   L3
    LINENUMBER 54 L3
    ALOAD 0
    ALOAD 1
    ILOAD 2
    ALOAD 5
    INVOKEVIRTUAL edu/utd/sonnv/Test.getCastingValue$$PHOSPHORTAGGED (Ledu/columbia/cs/psl/phosphor/runtime/Taint;ILedu/columbia/cs/psl/phosphor/struct/TaintedIntWithObjTag;)Ledu/columbia/cs/psl/phosphor/struct/TaintedIntWithObjTag;
    DUP
    GETFIELD edu/columbia/cs/psl/phosphor/struct/TaintedIntWithObjTag.taint : Ledu/columbia/cs/psl/phosphor/runtime/Taint;
    SWAP
    GETFIELD edu/columbia/cs/psl/phosphor/struct/TaintedIntWithObjTag.val : I
   L4
    ISTORE 6
    INVOKESTATIC edu/columbia/cs/psl/phosphor/runtime/Taint.copyTaint (Ledu/columbia/cs/psl/phosphor/runtime/Taint;)Ledu/columbia/cs/psl/phosphor/runtime/Taint;
    ASTORE 7
   L5
    LINENUMBER 55 L5
    ALOAD 0
    ALOAD 3
    ILOAD 4
    ALOAD 5
    INVOKEVIRTUAL edu/utd/sonnv/Test.getNormalValue$$PHOSPHORTAGGED (Ledu/columbia/cs/psl/phosphor/runtime/Taint;ILedu/columbia/cs/psl/phosphor/struct/TaintedIntWithObjTag;)Ledu/columbia/cs/psl/phosphor/struct/TaintedIntWithObjTag;
    GETFIELD edu/columbia/cs/psl/phosphor/struct/TaintedIntWithObjTag.val : I
    ISTORE 8
   L6
    LINENUMBER 56 L6
    ALOAD 0
    ALOAD 3
    ILOAD 4
    ALOAD 5
    INVOKEVIRTUAL edu/utd/sonnv/Test.getReturnPrimitiveConst$$PHOSPHORTAGGED (Ledu/columbia/cs/psl/phosphor/runtime/Taint;ILedu/columbia/cs/psl/phosphor/struct/TaintedIntWithObjTag;)Ledu/columbia/cs/psl/phosphor/struct/TaintedIntWithObjTag;
    DUP
    GETFIELD edu/columbia/cs/psl/phosphor/struct/TaintedIntWithObjTag.taint : Ledu/columbia/cs/psl/phosphor/runtime/Taint;
    SWAP
    GETFIELD edu/columbia/cs/psl/phosphor/struct/TaintedIntWithObjTag.val : I
   L7
    ISTORE 8
    INVOKESTATIC edu/columbia/cs/psl/phosphor/runtime/Taint.copyTaint (Ledu/columbia/cs/psl/phosphor/runtime/Taint;)Ledu/columbia/cs/psl/phosphor/runtime/Taint;
    ASTORE 9
   L8
    LINENUMBER 57 L8
   L9
    ALOAD 7
    ILOAD 6
   L10
    ALOAD 9
    ILOAD 8
   L11
    ISTORE 10
    SWAP
    ILOAD 10
   L12
    IADD
    DUP_X2
    POP
    INVOKESTATIC edu/columbia/cs/psl/phosphor/runtime/Taint.combineTags (Ledu/columbia/cs/psl/phosphor/runtime/Taint;Ledu/columbia/cs/psl/phosphor/runtime/Taint;)Ledu/columbia/cs/psl/phosphor/runtime/Taint;
    SWAP
    ALOAD 0
    ALOAD 3
    ILOAD 4
    ALOAD 5
    INVOKEVIRTUAL edu/utd/sonnv/Test.getNormalValue$$PHOSPHORTAGGED (Ledu/columbia/cs/psl/phosphor/runtime/Taint;ILedu/columbia/cs/psl/phosphor/struct/TaintedIntWithObjTag;)Ledu/columbia/cs/psl/phosphor/struct/TaintedIntWithObjTag;
    DUP
    GETFIELD edu/columbia/cs/psl/phosphor/struct/TaintedIntWithObjTag.taint : Ledu/columbia/cs/psl/phosphor/runtime/Taint;
    SWAP
    GETFIELD edu/columbia/cs/psl/phosphor/struct/TaintedIntWithObjTag.val : I
    ISTORE 10
    SWAP
    ILOAD 10
   L13
    IADD
    DUP_X2
    POP
    INVOKESTATIC edu/columbia/cs/psl/phosphor/runtime/Taint.combineTags (Ledu/columbia/cs/psl/phosphor/runtime/Taint;Ledu/columbia/cs/psl/phosphor/runtime/Taint;)Ledu/columbia/cs/psl/phosphor/runtime/Taint;
    SWAP
   L14
    ISTORE 11
    INVOKESTATIC edu/columbia/cs/psl/phosphor/runtime/Taint.copyTaint (Ledu/columbia/cs/psl/phosphor/runtime/Taint;)Ledu/columbia/cs/psl/phosphor/runtime/Taint;
    ASTORE 12
   L15
    LINENUMBER 58 L15
   L16
    ALOAD 12
    ILOAD 11
    LDC "edu.utd.sonnv.Test.testNomalCase"
    ALOAD 5
    INVOKESTATIC edu/columbia/cs/psl/phosphor/runtime/MultiTainter.taintedInt$$PHOSPHORTAGGED (Ledu/columbia/cs/psl/phosphor/runtime/Taint;ILjava/lang/Object;Ledu/columbia/cs/psl/phosphor/struct/TaintedIntWithObjTag;)Ledu/columbia/cs/psl/phosphor/struct/TaintedIntWithObjTag;
    DUP
    GETFIELD edu/columbia/cs/psl/phosphor/struct/TaintedIntWithObjTag.taint : Ledu/columbia/cs/psl/phosphor/runtime/Taint;
    SWAP
    GETFIELD edu/columbia/cs/psl/phosphor/struct/TaintedIntWithObjTag.val : I
    GETSTATIC java/lang/System.out : Ljava/io/PrintStream;
    LDC "Return: edu.utd.sonnv.Test.testNomalCase"
    INVOKEVIRTUAL java/io/PrintStream.println (Ljava/lang/String;)V
    ALOAD 5
    SWAP
    PUTFIELD edu/columbia/cs/psl/phosphor/struct/TaintedIntWithObjTag.val : I
    ALOAD 5
    SWAP
    PUTFIELD edu/columbia/cs/psl/phosphor/struct/TaintedIntWithObjTag.taint : Ledu/columbia/cs/psl/phosphor/runtime/Taint;
    ALOAD 5
    ARETURN
   L17
    LOCALVARIABLE this Ledu/utd/sonnv/Test; L3 L17 0
   L18
    LOCALVARIABLE phosphorShadowLVFor6XX0 Ledu/columbia/cs/psl/phosphor/runtime/Taint; L4 L9 7
    LOCALVARIABLE phosphorShadowLVFor11XX5 Ledu/columbia/cs/psl/phosphor/runtime/Taint; L14 L16 12
    LOCALVARIABLE phosphorShadowLV6 Ledu/columbia/cs/psl/phosphor/runtime/Taint; L16 L18 12
    LOCALVARIABLE phosphorShadowLV4 I L11 L13 10
    LOCALVARIABLE phosphorShadowLVFor8XX1 Ledu/columbia/cs/psl/phosphor/runtime/Taint; L7 L10 9
    LOCALVARIABLE phosphorShadowLV3 Ledu/columbia/cs/psl/phosphor/runtime/Taint; L10 L18 9
    LOCALVARIABLE phosphorShadowLV2 Ledu/columbia/cs/psl/phosphor/runtime/Taint; L9 L18 7
    LOCALVARIABLE input1_TAINT Ledu/columbia/cs/psl/phosphor/runtime/Taint; L3 L17 1
    LOCALVARIABLE input1 I L3 L17 2
    LOCALVARIABLE input2_TAINT Ledu/columbia/cs/psl/phosphor/runtime/Taint; L3 L17 3
    LOCALVARIABLE input2 I L3 L17 4
    LOCALVARIABLE PHOSPHORPREALLOCRETURNHAHA Ledu/columbia/cs/psl/phosphor/struct/TaintedIntWithObjTag; L3 L17 5
    LOCALVARIABLE a I L5 L17 6
    LOCALVARIABLE b I L6 L17 8
    LOCALVARIABLE c I L15 L17 11
    MAXSTACK = 103
    MAXLOCALS = 13

  // access flags 0x1
  public testArrayUsage$$PHOSPHORTAGGED(Ledu/columbia/cs/psl/phosphor/runtime/Taint;ILedu/columbia/cs/psl/phosphor/struct/TaintedIntWithObjTag;)Ledu/columbia/cs/psl/phosphor/struct/TaintedIntWithObjTag;
   L0
   L1
   L2
    ALOAD 1
    ILOAD 2
    ACONST_NULL
    ALOAD 3
    INVOKESTATIC edu/columbia/cs/psl/phosphor/runtime/MultiTainter.taintedInt$$PHOSPHORTAGGED (Ledu/columbia/cs/psl/phosphor/runtime/Taint;ILjava/lang/Object;Ledu/columbia/cs/psl/phosphor/struct/TaintedIntWithObjTag;)Ledu/columbia/cs/psl/phosphor/struct/TaintedIntWithObjTag;
    DUP
    GETFIELD edu/columbia/cs/psl/phosphor/struct/TaintedIntWithObjTag.taint : Ledu/columbia/cs/psl/phosphor/runtime/Taint;
    SWAP
    GETFIELD edu/columbia/cs/psl/phosphor/struct/TaintedIntWithObjTag.val : I
    ISTORE 2
    INVOKESTATIC edu/columbia/cs/psl/phosphor/runtime/Taint.copyTaint (Ledu/columbia/cs/psl/phosphor/runtime/Taint;)Ledu/columbia/cs/psl/phosphor/runtime/Taint;
    ASTORE 1
   L3
    LINENUMBER 62 L3
    ALOAD 0
    ALOAD 1
    ILOAD 2
    INVOKEVIRTUAL edu/utd/sonnv/Test.getArray$$PHOSPHORTAGGED (Ledu/columbia/cs/psl/phosphor/runtime/Taint;I)Ledu/columbia/cs/psl/phosphor/struct/LazyIntArrayObjTags;
    DUP
    IFNULL L4
    DUP
    GETFIELD edu/columbia/cs/psl/phosphor/struct/LazyIntArrayObjTags.val : [I
    GOTO L5
   L4
   FRAME FULL [edu/utd/sonnv/Test edu/columbia/cs/psl/phosphor/runtime/Taint I edu/columbia/cs/psl/phosphor/struct/TaintedIntWithObjTag] [edu/columbia/cs/psl/phosphor/struct/LazyIntArrayObjTags]
    ACONST_NULL
    CHECKCAST [I
   L5
   FRAME FULL [edu/utd/sonnv/Test edu/columbia/cs/psl/phosphor/runtime/Taint I edu/columbia/cs/psl/phosphor/struct/TaintedIntWithObjTag] [edu/columbia/cs/psl/phosphor/struct/LazyIntArrayObjTags [I]
   L6
    ASTORE 4
    ASTORE 5
   L7
    LINENUMBER 63 L7
    ALOAD 5
    ALOAD 4
    ICONST_0
    ALOAD 3
    INVOKEVIRTUAL edu/columbia/cs/psl/phosphor/struct/LazyIntArrayObjTags.get ([IILedu/columbia/cs/psl/phosphor/struct/TaintedIntWithObjTag;)Ledu/columbia/cs/psl/phosphor/struct/TaintedIntWithObjTag;
    DUP
    GETFIELD edu/columbia/cs/psl/phosphor/struct/TaintedIntWithObjTag.taint : Ledu/columbia/cs/psl/phosphor/runtime/Taint;
    SWAP
    GETFIELD edu/columbia/cs/psl/phosphor/struct/TaintedIntWithObjTag.val : I
    LDC "edu.utd.sonnv.Test.testArrayUsage"
    ALOAD 3
    INVOKESTATIC edu/columbia/cs/psl/phosphor/runtime/MultiTainter.taintedInt$$PHOSPHORTAGGED (Ledu/columbia/cs/psl/phosphor/runtime/Taint;ILjava/lang/Object;Ledu/columbia/cs/psl/phosphor/struct/TaintedIntWithObjTag;)Ledu/columbia/cs/psl/phosphor/struct/TaintedIntWithObjTag;
    DUP
    GETFIELD edu/columbia/cs/psl/phosphor/struct/TaintedIntWithObjTag.taint : Ledu/columbia/cs/psl/phosphor/runtime/Taint;
    SWAP
    GETFIELD edu/columbia/cs/psl/phosphor/struct/TaintedIntWithObjTag.val : I
    GETSTATIC java/lang/System.out : Ljava/io/PrintStream;
    LDC "Return: edu.utd.sonnv.Test.testArrayUsage"
    INVOKEVIRTUAL java/io/PrintStream.println (Ljava/lang/String;)V
    ALOAD 3
    SWAP
    PUTFIELD edu/columbia/cs/psl/phosphor/struct/TaintedIntWithObjTag.val : I
    ALOAD 3
    SWAP
    PUTFIELD edu/columbia/cs/psl/phosphor/struct/TaintedIntWithObjTag.taint : Ledu/columbia/cs/psl/phosphor/runtime/Taint;
    ALOAD 3
    ARETURN
   L8
    LOCALVARIABLE this Ledu/utd/sonnv/Test; L3 L8 0
   L9
    LOCALVARIABLE phosphorShadowLVFor4XX0 Ledu/columbia/cs/psl/phosphor/struct/LazyIntArrayObjTags; L6 L9 5
    LOCALVARIABLE x_TAINT Ledu/columbia/cs/psl/phosphor/runtime/Taint; L3 L8 1
    LOCALVARIABLE x I L3 L8 2
    LOCALVARIABLE PHOSPHORPREALLOCRETURNHAHA Ledu/columbia/cs/psl/phosphor/struct/TaintedIntWithObjTag; L3 L8 3
    LOCALVARIABLE array [I L7 L8 4
    MAXSTACK = 103
    MAXLOCALS = 6

  // access flags 0x1
  public getArray$$PHOSPHORTAGGED(Ledu/columbia/cs/psl/phosphor/runtime/Taint;I)Ledu/columbia/cs/psl/phosphor/struct/LazyIntArrayObjTags;
   L0
   L1
   L2
    NEW edu/columbia/cs/psl/phosphor/struct/TaintedIntWithObjTag
    DUP
    INVOKESPECIAL edu/columbia/cs/psl/phosphor/struct/TaintedIntWithObjTag.<init> ()V
    ASTORE 3
   L3
    ALOAD 1
    ILOAD 2
    ACONST_NULL
    ALOAD 3
    INVOKESTATIC edu/columbia/cs/psl/phosphor/runtime/MultiTainter.taintedInt$$PHOSPHORTAGGED (Ledu/columbia/cs/psl/phosphor/runtime/Taint;ILjava/lang/Object;Ledu/columbia/cs/psl/phosphor/struct/TaintedIntWithObjTag;)Ledu/columbia/cs/psl/phosphor/struct/TaintedIntWithObjTag;
    DUP
    GETFIELD edu/columbia/cs/psl/phosphor/struct/TaintedIntWithObjTag.taint : Ledu/columbia/cs/psl/phosphor/runtime/Taint;
    SWAP
    GETFIELD edu/columbia/cs/psl/phosphor/struct/TaintedIntWithObjTag.val : I
    ISTORE 2
    INVOKESTATIC edu/columbia/cs/psl/phosphor/runtime/Taint.copyTaint (Ledu/columbia/cs/psl/phosphor/runtime/Taint;)Ledu/columbia/cs/psl/phosphor/runtime/Taint;
    ASTORE 1
   L4
    LINENUMBER 68 L4
    ALOAD 0
    ALOAD 1
    ILOAD 2
    ALOAD 3
    INVOKEVIRTUAL edu/utd/sonnv/Test.getNormalValue$$PHOSPHORTAGGED (Ledu/columbia/cs/psl/phosphor/runtime/Taint;ILedu/columbia/cs/psl/phosphor/struct/TaintedIntWithObjTag;)Ledu/columbia/cs/psl/phosphor/struct/TaintedIntWithObjTag;
    GETFIELD edu/columbia/cs/psl/phosphor/struct/TaintedIntWithObjTag.val : I
    NEWARRAY T_INT
    DUP
   L5
    NEW edu/columbia/cs/psl/phosphor/struct/LazyIntArrayObjTags
    DUP_X1
    SWAP
    INVOKESPECIAL edu/columbia/cs/psl/phosphor/struct/LazyIntArrayObjTags.<init> ([I)V
    SWAP
   L6
    ASTORE 4
    ASTORE 5
   L7
    LINENUMBER 69 L7
    ACONST_NULL
    ICONST_0
   L8
    ISTORE 6
    INVOKESTATIC edu/columbia/cs/psl/phosphor/runtime/Taint.copyTaint (Ledu/columbia/cs/psl/phosphor/runtime/Taint;)Ledu/columbia/cs/psl/phosphor/runtime/Taint;
    ASTORE 7
   L9
   FRAME FULL [edu/utd/sonnv/Test edu/columbia/cs/psl/phosphor/runtime/Taint I edu/columbia/cs/psl/phosphor/struct/TaintedIntWithObjTag [I edu/columbia/cs/psl/phosphor/struct/LazyIntArrayObjTags I edu/columbia/cs/psl/phosphor/runtime/Taint] []
    ILOAD 6
    ILOAD 2
    IF_ICMPGE L10
   L11
   L12
    LINENUMBER 70 L12
    ALOAD 5
    ALOAD 4
    ILOAD 6
   L13
    ALOAD 7
    ILOAD 6
    INVOKEVIRTUAL edu/columbia/cs/psl/phosphor/struct/LazyIntArrayObjTags.set ([IILedu/columbia/cs/psl/phosphor/runtime/Taint;I)V
   L14
    LINENUMBER 69 L14
    IINC 6 1
    GOTO L9
   L15
   L10
    LINENUMBER 72 L10
   FRAME FULL [edu/utd/sonnv/Test edu/columbia/cs/psl/phosphor/runtime/Taint I edu/columbia/cs/psl/phosphor/struct/TaintedIntWithObjTag [I edu/columbia/cs/psl/phosphor/struct/LazyIntArrayObjTags I edu/columbia/cs/psl/phosphor/runtime/Taint] []
    ALOAD 5
    ALOAD 4
    ILOAD 2
    ALOAD 0
    ALOAD 1
    ILOAD 2
    ALOAD 3
    INVOKEVIRTUAL edu/utd/sonnv/Test.getReturnPrimitiveConst$$PHOSPHORTAGGED (Ledu/columbia/cs/psl/phosphor/runtime/Taint;ILedu/columbia/cs/psl/phosphor/struct/TaintedIntWithObjTag;)Ledu/columbia/cs/psl/phosphor/struct/TaintedIntWithObjTag;
    DUP
    GETFIELD edu/columbia/cs/psl/phosphor/struct/TaintedIntWithObjTag.taint : Ledu/columbia/cs/psl/phosphor/runtime/Taint;
    SWAP
    GETFIELD edu/columbia/cs/psl/phosphor/struct/TaintedIntWithObjTag.val : I
    INVOKEVIRTUAL edu/columbia/cs/psl/phosphor/struct/LazyIntArrayObjTags.set ([IILedu/columbia/cs/psl/phosphor/runtime/Taint;I)V
   L16
    LINENUMBER 73 L16
    ALOAD 5
    ALOAD 4
    ILOAD 2
    ICONST_1
    IADD
    ALOAD 0
    ALOAD 1
    ILOAD 2
    ALOAD 3
    INVOKEVIRTUAL edu/utd/sonnv/Test.getCastingValue$$PHOSPHORTAGGED (Ledu/columbia/cs/psl/phosphor/runtime/Taint;ILedu/columbia/cs/psl/phosphor/struct/TaintedIntWithObjTag;)Ledu/columbia/cs/psl/phosphor/struct/TaintedIntWithObjTag;
    DUP
    GETFIELD edu/columbia/cs/psl/phosphor/struct/TaintedIntWithObjTag.taint : Ledu/columbia/cs/psl/phosphor/runtime/Taint;
    SWAP
    GETFIELD edu/columbia/cs/psl/phosphor/struct/TaintedIntWithObjTag.val : I
    INVOKEVIRTUAL edu/columbia/cs/psl/phosphor/struct/LazyIntArrayObjTags.set ([IILedu/columbia/cs/psl/phosphor/runtime/Taint;I)V
   L17
    LINENUMBER 74 L17
    ALOAD 5
    ALOAD 4
    LDC "edu.utd.sonnv.Test.getArray"
    INVOKESTATIC edu/columbia/cs/psl/phosphor/runtime/MultiTainter.taintedIntArray$$PHOSPHORTAGGED (Ledu/columbia/cs/psl/phosphor/struct/LazyIntArrayObjTags;[ILjava/lang/Object;)Ledu/columbia/cs/psl/phosphor/struct/LazyIntArrayObjTags;
    DUP
    IFNULL L18
    DUP
    GETFIELD edu/columbia/cs/psl/phosphor/struct/LazyIntArrayObjTags.val : [I
    GOTO L19
   L18
   FRAME FULL [edu/utd/sonnv/Test edu/columbia/cs/psl/phosphor/runtime/Taint I edu/columbia/cs/psl/phosphor/struct/TaintedIntWithObjTag [I edu/columbia/cs/psl/phosphor/struct/LazyIntArrayObjTags I edu/columbia/cs/psl/phosphor/runtime/Taint] [edu/columbia/cs/psl/phosphor/struct/LazyIntArrayObjTags]
    ACONST_NULL
    CHECKCAST [I
   L19
   FRAME FULL [edu/utd/sonnv/Test edu/columbia/cs/psl/phosphor/runtime/Taint I edu/columbia/cs/psl/phosphor/struct/TaintedIntWithObjTag [I edu/columbia/cs/psl/phosphor/struct/LazyIntArrayObjTags I edu/columbia/cs/psl/phosphor/runtime/Taint] [edu/columbia/cs/psl/phosphor/struct/LazyIntArrayObjTags [I]
    GETSTATIC java/lang/System.out : Ljava/io/PrintStream;
    LDC "Return: edu.utd.sonnv.Test.getArray"
    INVOKEVIRTUAL java/io/PrintStream.println (Ljava/lang/String;)V
    SWAP
    DUP
    IFNULL L20
    DUP_X1
    SWAP
    INVOKEVIRTUAL edu/columbia/cs/psl/phosphor/struct/LazyIntArrayObjTags.ensureVal ([I)V
    GOTO L21
   L20
   FRAME FULL [edu/utd/sonnv/Test edu/columbia/cs/psl/phosphor/runtime/Taint I edu/columbia/cs/psl/phosphor/struct/TaintedIntWithObjTag [I edu/columbia/cs/psl/phosphor/struct/LazyIntArrayObjTags I edu/columbia/cs/psl/phosphor/runtime/Taint] [[I edu/columbia/cs/psl/phosphor/struct/LazyIntArrayObjTags]
    SWAP
    POP
   L21
   FRAME FULL [edu/utd/sonnv/Test edu/columbia/cs/psl/phosphor/runtime/Taint I edu/columbia/cs/psl/phosphor/struct/TaintedIntWithObjTag [I edu/columbia/cs/psl/phosphor/struct/LazyIntArrayObjTags I edu/columbia/cs/psl/phosphor/runtime/Taint] [edu/columbia/cs/psl/phosphor/struct/LazyIntArrayObjTags]
    ARETURN
   L22
    LOCALVARIABLE i I L9 L10 6
   L23
    LOCALVARIABLE phosphorReturnPreAlloc0 Ledu/columbia/cs/psl/phosphor/struct/TaintedIntWithObjTag; L2 L23 3
    LOCALVARIABLE phosphorShadowLVFor6XX2 Ledu/columbia/cs/psl/phosphor/runtime/Taint; L8 L13 7
    LOCALVARIABLE phosphorShadowLVFor4XX1 Ledu/columbia/cs/psl/phosphor/struct/LazyIntArrayObjTags; L6 L23 5
    LOCALVARIABLE phosphorShadowLV3 Ledu/columbia/cs/psl/phosphor/runtime/Taint; L13 L23 7
    LOCALVARIABLE this Ledu/utd/sonnv/Test; L4 L22 0
    LOCALVARIABLE x_TAINT Ledu/columbia/cs/psl/phosphor/runtime/Taint; L4 L22 1
    LOCALVARIABLE x I L4 L22 2
    LOCALVARIABLE y [I L7 L22 4
    MAXSTACK = 104
    MAXLOCALS = 8

  // access flags 0x1
  public getCastingValue$$PHOSPHORTAGGED(Ledu/columbia/cs/psl/phosphor/runtime/Taint;ILedu/columbia/cs/psl/phosphor/struct/TaintedIntWithObjTag;)Ledu/columbia/cs/psl/phosphor/struct/TaintedIntWithObjTag;
   L0
   L1
   L2
    ALOAD 1
    ILOAD 2
    ACONST_NULL
    ALOAD 3
    INVOKESTATIC edu/columbia/cs/psl/phosphor/runtime/MultiTainter.taintedInt$$PHOSPHORTAGGED (Ledu/columbia/cs/psl/phosphor/runtime/Taint;ILjava/lang/Object;Ledu/columbia/cs/psl/phosphor/struct/TaintedIntWithObjTag;)Ledu/columbia/cs/psl/phosphor/struct/TaintedIntWithObjTag;
    DUP
    GETFIELD edu/columbia/cs/psl/phosphor/struct/TaintedIntWithObjTag.taint : Ledu/columbia/cs/psl/phosphor/runtime/Taint;
    SWAP
    GETFIELD edu/columbia/cs/psl/phosphor/struct/TaintedIntWithObjTag.val : I
    ISTORE 2
    INVOKESTATIC edu/columbia/cs/psl/phosphor/runtime/Taint.copyTaint (Ledu/columbia/cs/psl/phosphor/runtime/Taint;)Ledu/columbia/cs/psl/phosphor/runtime/Taint;
    ASTORE 1
   L3
    LINENUMBER 78 L3
    ACONST_NULL
    LDC 3.0
   L4
    FSTORE 4
    INVOKESTATIC edu/columbia/cs/psl/phosphor/runtime/Taint.copyTaint (Ledu/columbia/cs/psl/phosphor/runtime/Taint;)Ledu/columbia/cs/psl/phosphor/runtime/Taint;
    ASTORE 5
   L5
    LINENUMBER 79 L5
    ALOAD 1
    ILOAD 2
    I2F
   L6
    ALOAD 5
    FLOAD 4
   L7
    FSTORE 6
    SWAP
    FLOAD 6
    FADD
    DUP_X2
    POP
    INVOKESTATIC edu/columbia/cs/psl/phosphor/runtime/Taint.combineTags (Ledu/columbia/cs/psl/phosphor/runtime/Taint;Ledu/columbia/cs/psl/phosphor/runtime/Taint;)Ledu/columbia/cs/psl/phosphor/runtime/Taint;
    SWAP
   L8
    F2I
    LDC "edu.utd.sonnv.Test.getCastingValue"
    ALOAD 3
    INVOKESTATIC edu/columbia/cs/psl/phosphor/runtime/MultiTainter.taintedInt$$PHOSPHORTAGGED (Ledu/columbia/cs/psl/phosphor/runtime/Taint;ILjava/lang/Object;Ledu/columbia/cs/psl/phosphor/struct/TaintedIntWithObjTag;)Ledu/columbia/cs/psl/phosphor/struct/TaintedIntWithObjTag;
    DUP
    GETFIELD edu/columbia/cs/psl/phosphor/struct/TaintedIntWithObjTag.taint : Ledu/columbia/cs/psl/phosphor/runtime/Taint;
    SWAP
    GETFIELD edu/columbia/cs/psl/phosphor/struct/TaintedIntWithObjTag.val : I
    GETSTATIC java/lang/System.out : Ljava/io/PrintStream;
    LDC "Return: edu.utd.sonnv.Test.getCastingValue"
    INVOKEVIRTUAL java/io/PrintStream.println (Ljava/lang/String;)V
    ALOAD 3
    SWAP
    PUTFIELD edu/columbia/cs/psl/phosphor/struct/TaintedIntWithObjTag.val : I
    ALOAD 3
    SWAP
    PUTFIELD edu/columbia/cs/psl/phosphor/struct/TaintedIntWithObjTag.taint : Ledu/columbia/cs/psl/phosphor/runtime/Taint;
    ALOAD 3
    ARETURN
   L9
    LOCALVARIABLE this Ledu/utd/sonnv/Test; L3 L9 0
   L10
    LOCALVARIABLE phosphorShadowLV2 F L7 L8 6
    LOCALVARIABLE phosphorShadowLVFor4XX0 Ledu/columbia/cs/psl/phosphor/runtime/Taint; L4 L6 5
    LOCALVARIABLE phosphorShadowLV1 Ledu/columbia/cs/psl/phosphor/runtime/Taint; L6 L10 5
    LOCALVARIABLE x_TAINT Ledu/columbia/cs/psl/phosphor/runtime/Taint; L3 L9 1
    LOCALVARIABLE x I L3 L9 2
    LOCALVARIABLE PHOSPHORPREALLOCRETURNHAHA Ledu/columbia/cs/psl/phosphor/struct/TaintedIntWithObjTag; L3 L9 3
    LOCALVARIABLE f F L5 L9 4
    MAXSTACK = 103
    MAXLOCALS = 7

  // access flags 0x1
  public getNormalValue$$PHOSPHORTAGGED(Ledu/columbia/cs/psl/phosphor/runtime/Taint;ILedu/columbia/cs/psl/phosphor/struct/TaintedIntWithObjTag;)Ledu/columbia/cs/psl/phosphor/struct/TaintedIntWithObjTag;
   L0
   L1
   L2
    NEW edu/columbia/cs/psl/phosphor/struct/TaintedShortWithObjTag
    DUP
    INVOKESPECIAL edu/columbia/cs/psl/phosphor/struct/TaintedShortWithObjTag.<init> ()V
    ASTORE 4
   L3
    ALOAD 1
    ILOAD 2
    ACONST_NULL
    ALOAD 3
    INVOKESTATIC edu/columbia/cs/psl/phosphor/runtime/MultiTainter.taintedInt$$PHOSPHORTAGGED (Ledu/columbia/cs/psl/phosphor/runtime/Taint;ILjava/lang/Object;Ledu/columbia/cs/psl/phosphor/struct/TaintedIntWithObjTag;)Ledu/columbia/cs/psl/phosphor/struct/TaintedIntWithObjTag;
    DUP
    GETFIELD edu/columbia/cs/psl/phosphor/struct/TaintedIntWithObjTag.taint : Ledu/columbia/cs/psl/phosphor/runtime/Taint;
    SWAP
    GETFIELD edu/columbia/cs/psl/phosphor/struct/TaintedIntWithObjTag.val : I
    ISTORE 2
    INVOKESTATIC edu/columbia/cs/psl/phosphor/runtime/Taint.copyTaint (Ledu/columbia/cs/psl/phosphor/runtime/Taint;)Ledu/columbia/cs/psl/phosphor/runtime/Taint;
    ASTORE 1
   L4
    LINENUMBER 83 L4
    ALOAD 0
    ALOAD 1
    ILOAD 2
    ALOAD 4
    INVOKEVIRTUAL edu/utd/sonnv/Test.getValue4$$PHOSPHORTAGGED (Ledu/columbia/cs/psl/phosphor/runtime/Taint;ILedu/columbia/cs/psl/phosphor/struct/TaintedShortWithObjTag;)Ledu/columbia/cs/psl/phosphor/struct/TaintedShortWithObjTag;
    DUP
    GETFIELD edu/columbia/cs/psl/phosphor/struct/TaintedShortWithObjTag.taint : Ledu/columbia/cs/psl/phosphor/runtime/Taint;
    SWAP
    GETFIELD edu/columbia/cs/psl/phosphor/struct/TaintedShortWithObjTag.val : S
    ACONST_NULL
    ICONST_3
   L5
    ISTORE 5
    SWAP
    ILOAD 5
   L6
    IADD
    DUP_X2
    POP
    INVOKESTATIC edu/columbia/cs/psl/phosphor/runtime/Taint.combineTags (Ledu/columbia/cs/psl/phosphor/runtime/Taint;Ledu/columbia/cs/psl/phosphor/runtime/Taint;)Ledu/columbia/cs/psl/phosphor/runtime/Taint;
    SWAP
    LDC "edu.utd.sonnv.Test.getNormalValue"
    ALOAD 3
    INVOKESTATIC edu/columbia/cs/psl/phosphor/runtime/MultiTainter.taintedInt$$PHOSPHORTAGGED (Ledu/columbia/cs/psl/phosphor/runtime/Taint;ILjava/lang/Object;Ledu/columbia/cs/psl/phosphor/struct/TaintedIntWithObjTag;)Ledu/columbia/cs/psl/phosphor/struct/TaintedIntWithObjTag;
    DUP
    GETFIELD edu/columbia/cs/psl/phosphor/struct/TaintedIntWithObjTag.taint : Ledu/columbia/cs/psl/phosphor/runtime/Taint;
    SWAP
    GETFIELD edu/columbia/cs/psl/phosphor/struct/TaintedIntWithObjTag.val : I
    GETSTATIC java/lang/System.out : Ljava/io/PrintStream;
    LDC "Return: edu.utd.sonnv.Test.getNormalValue"
    INVOKEVIRTUAL java/io/PrintStream.println (Ljava/lang/String;)V
    ALOAD 3
    SWAP
    PUTFIELD edu/columbia/cs/psl/phosphor/struct/TaintedIntWithObjTag.val : I
    ALOAD 3
    SWAP
    PUTFIELD edu/columbia/cs/psl/phosphor/struct/TaintedIntWithObjTag.taint : Ledu/columbia/cs/psl/phosphor/runtime/Taint;
    ALOAD 3
    ARETURN
   L7
    LOCALVARIABLE this Ledu/utd/sonnv/Test; L4 L7 0
   L8
    LOCALVARIABLE phosphorReturnPreAlloc0 Ledu/columbia/cs/psl/phosphor/struct/TaintedShortWithObjTag; L2 L8 4
    LOCALVARIABLE phosphorShadowLV1 I L5 L6 5
    LOCALVARIABLE x_TAINT Ledu/columbia/cs/psl/phosphor/runtime/Taint; L4 L7 1
    LOCALVARIABLE x I L4 L7 2
    LOCALVARIABLE PHOSPHORPREALLOCRETURNHAHA Ledu/columbia/cs/psl/phosphor/struct/TaintedIntWithObjTag; L4 L7 3
    MAXSTACK = 103
    MAXLOCALS = 6

  // access flags 0x1
  public getReturnPrimitiveConst$$PHOSPHORTAGGED(Ledu/columbia/cs/psl/phosphor/runtime/Taint;ILedu/columbia/cs/psl/phosphor/struct/TaintedIntWithObjTag;)Ledu/columbia/cs/psl/phosphor/struct/TaintedIntWithObjTag;
   L0
   L1
   L2
    ALOAD 1
    ILOAD 2
    ACONST_NULL
    ALOAD 3
    INVOKESTATIC edu/columbia/cs/psl/phosphor/runtime/MultiTainter.taintedInt$$PHOSPHORTAGGED (Ledu/columbia/cs/psl/phosphor/runtime/Taint;ILjava/lang/Object;Ledu/columbia/cs/psl/phosphor/struct/TaintedIntWithObjTag;)Ledu/columbia/cs/psl/phosphor/struct/TaintedIntWithObjTag;
    GETFIELD edu/columbia/cs/psl/phosphor/struct/TaintedIntWithObjTag.val : I
    ISTORE 2
   L3
    LINENUMBER 87 L3
    ACONST_NULL
    BIPUSH 9
    LDC "edu.utd.sonnv.Test.getReturnPrimitiveConst"
    ALOAD 3
    INVOKESTATIC edu/columbia/cs/psl/phosphor/runtime/MultiTainter.taintedInt$$PHOSPHORTAGGED (Ledu/columbia/cs/psl/phosphor/runtime/Taint;ILjava/lang/Object;Ledu/columbia/cs/psl/phosphor/struct/TaintedIntWithObjTag;)Ledu/columbia/cs/psl/phosphor/struct/TaintedIntWithObjTag;
    DUP
    GETFIELD edu/columbia/cs/psl/phosphor/struct/TaintedIntWithObjTag.taint : Ledu/columbia/cs/psl/phosphor/runtime/Taint;
    SWAP
    GETFIELD edu/columbia/cs/psl/phosphor/struct/TaintedIntWithObjTag.val : I
    GETSTATIC java/lang/System.out : Ljava/io/PrintStream;
    LDC "Return: edu.utd.sonnv.Test.getReturnPrimitiveConst"
    INVOKEVIRTUAL java/io/PrintStream.println (Ljava/lang/String;)V
    ALOAD 3
    SWAP
    PUTFIELD edu/columbia/cs/psl/phosphor/struct/TaintedIntWithObjTag.val : I
    ALOAD 3
    SWAP
    PUTFIELD edu/columbia/cs/psl/phosphor/struct/TaintedIntWithObjTag.taint : Ledu/columbia/cs/psl/phosphor/runtime/Taint;
    ALOAD 3
    ARETURN
   L4
    LOCALVARIABLE this Ledu/utd/sonnv/Test; L3 L4 0
    LOCALVARIABLE x_TAINT Ledu/columbia/cs/psl/phosphor/runtime/Taint; L3 L4 1
    LOCALVARIABLE x I L3 L4 2
    LOCALVARIABLE PHOSPHORPREALLOCRETURNHAHA Ledu/columbia/cs/psl/phosphor/struct/TaintedIntWithObjTag; L3 L4 3
   L5
    MAXSTACK = 103
    MAXLOCALS = 4

  // access flags 0x1
  public getValue4$$PHOSPHORTAGGED(Ledu/columbia/cs/psl/phosphor/runtime/Taint;ILedu/columbia/cs/psl/phosphor/struct/TaintedShortWithObjTag;)Ledu/columbia/cs/psl/phosphor/struct/TaintedShortWithObjTag;
   L0
   L1
   L2
    NEW edu/columbia/cs/psl/phosphor/struct/TaintedIntWithObjTag
    DUP
    INVOKESPECIAL edu/columbia/cs/psl/phosphor/struct/TaintedIntWithObjTag.<init> ()V
    ASTORE 4
   L3
    ALOAD 1
    ILOAD 2
    ACONST_NULL
    ALOAD 4
    INVOKESTATIC edu/columbia/cs/psl/phosphor/runtime/MultiTainter.taintedInt$$PHOSPHORTAGGED (Ledu/columbia/cs/psl/phosphor/runtime/Taint;ILjava/lang/Object;Ledu/columbia/cs/psl/phosphor/struct/TaintedIntWithObjTag;)Ledu/columbia/cs/psl/phosphor/struct/TaintedIntWithObjTag;
    DUP
    GETFIELD edu/columbia/cs/psl/phosphor/struct/TaintedIntWithObjTag.taint : Ledu/columbia/cs/psl/phosphor/runtime/Taint;
    SWAP
    GETFIELD edu/columbia/cs/psl/phosphor/struct/TaintedIntWithObjTag.val : I
    ISTORE 2
    INVOKESTATIC edu/columbia/cs/psl/phosphor/runtime/Taint.copyTaint (Ledu/columbia/cs/psl/phosphor/runtime/Taint;)Ledu/columbia/cs/psl/phosphor/runtime/Taint;
    ASTORE 1
   L4
    LINENUMBER 91 L4
    ALOAD 1
    ILOAD 2
    I2S
   L5
    ISTORE 5
    INVOKESTATIC edu/columbia/cs/psl/phosphor/runtime/Taint.copyTaint (Ledu/columbia/cs/psl/phosphor/runtime/Taint;)Ledu/columbia/cs/psl/phosphor/runtime/Taint;
    ASTORE 6
   L6
    LINENUMBER 92 L6
   L7
    ALOAD 6
    ILOAD 5
    LDC "edu.utd.sonnv.Test.getValue4"
    ALOAD 3
    INVOKESTATIC edu/columbia/cs/psl/phosphor/runtime/MultiTainter.taintedShort$$PHOSPHORTAGGED (Ledu/columbia/cs/psl/phosphor/runtime/Taint;SLjava/lang/Object;Ledu/columbia/cs/psl/phosphor/struct/TaintedShortWithObjTag;)Ledu/columbia/cs/psl/phosphor/struct/TaintedShortWithObjTag;
    DUP
    GETFIELD edu/columbia/cs/psl/phosphor/struct/TaintedShortWithObjTag.taint : Ledu/columbia/cs/psl/phosphor/runtime/Taint;
    SWAP
    GETFIELD edu/columbia/cs/psl/phosphor/struct/TaintedShortWithObjTag.val : S
    GETSTATIC java/lang/System.out : Ljava/io/PrintStream;
    LDC "Return: edu.utd.sonnv.Test.getValue4"
    INVOKEVIRTUAL java/io/PrintStream.println (Ljava/lang/String;)V
    ALOAD 3
    SWAP
    PUTFIELD edu/columbia/cs/psl/phosphor/struct/TaintedShortWithObjTag.val : S
    ALOAD 3
    SWAP
    PUTFIELD edu/columbia/cs/psl/phosphor/struct/TaintedShortWithObjTag.taint : Ledu/columbia/cs/psl/phosphor/runtime/Taint;
    ALOAD 3
    ARETURN
   L8
    LOCALVARIABLE this Ledu/utd/sonnv/Test; L4 L8 0
   L9
    LOCALVARIABLE phosphorReturnPreAlloc0 Ledu/columbia/cs/psl/phosphor/struct/TaintedIntWithObjTag; L2 L9 4
    LOCALVARIABLE phosphorShadowLV2 Ledu/columbia/cs/psl/phosphor/runtime/Taint; L7 L9 6
    LOCALVARIABLE phosphorShadowLVFor5XX1 Ledu/columbia/cs/psl/phosphor/runtime/Taint; L5 L7 6
    LOCALVARIABLE x_TAINT Ledu/columbia/cs/psl/phosphor/runtime/Taint; L4 L8 1
    LOCALVARIABLE x I L4 L8 2
    LOCALVARIABLE PHOSPHORPREALLOCRETURNHAHA Ledu/columbia/cs/psl/phosphor/struct/TaintedShortWithObjTag; L4 L8 3
    LOCALVARIABLE y S L6 L8 5
    MAXSTACK = 103
    MAXLOCALS = 7

  // access flags 0x1
  public testThrow(Ljava/lang/String;)V
   L0
   L1
   L2
    NEW edu/columbia/cs/psl/phosphor/struct/TaintedIntWithObjTag
    DUP
    INVOKESPECIAL edu/columbia/cs/psl/phosphor/struct/TaintedIntWithObjTag.<init> ()V
    ASTORE 2
    TRYCATCHBLOCK L3 L4 L5 java/lang/Exception
   L6
   L3
    LINENUMBER 97 L3
    ALOAD 1
    ALOAD 2
    INVOKESTATIC edu/columbia/cs/psl/phosphor/runtime/RuntimeBoxUnboxPropogator.parseInt$$PHOSPHORTAGGED (Ljava/lang/String;Ledu/columbia/cs/psl/phosphor/struct/TaintedIntWithObjTag;)Ledu/columbia/cs/psl/phosphor/struct/TaintedIntWithObjTag;
    GETFIELD edu/columbia/cs/psl/phosphor/struct/TaintedIntWithObjTag.val : I
    ISTORE 3
   L4
    LINENUMBER 100 L4
    GOTO L7
   L8
   L5
    LINENUMBER 98 L5
   FRAME FULL [edu/utd/sonnv/Test java/lang/String edu/columbia/cs/psl/phosphor/struct/TaintedIntWithObjTag] [java/lang/Exception]
    ASTORE 3
   L9
    LINENUMBER 99 L9
    NEW java/lang/NumberFormatException
    DUP
    INVOKESPECIAL java/lang/NumberFormatException.<init> ()V
    ATHROW
   L7
    LINENUMBER 101 L7
   FRAME FULL [edu/utd/sonnv/Test java/lang/String edu/columbia/cs/psl/phosphor/struct/TaintedIntWithObjTag I] []
    GETSTATIC java/lang/System.out : Ljava/io/PrintStream;
    LDC "Void: edu.utd.sonnv.Test.testThrow"
    INVOKEVIRTUAL java/io/PrintStream.println (Ljava/lang/String;)V
    RETURN
   L10
    LOCALVARIABLE e Ljava/lang/Exception; L9 L7 3
   L11
    LOCALVARIABLE phosphorReturnPreAlloc0 Ledu/columbia/cs/psl/phosphor/struct/TaintedIntWithObjTag; L2 L11 2
    LOCALVARIABLE this Ledu/utd/sonnv/Test; L3 L10 0
    LOCALVARIABLE a Ljava/lang/String; L3 L10 1
    MAXSTACK = 102
    MAXLOCALS = 4

  // access flags 0x1
  public testTernaryWithPrimitive$$PHOSPHORTAGGED(Ledu/columbia/cs/psl/phosphor/struct/TaintedIntWithObjTag;)Ledu/columbia/cs/psl/phosphor/struct/TaintedIntWithObjTag;
   L0
   L1
   L2
   L3
    LINENUMBER 104 L3
    ALOAD 0
    ACONST_NULL
    ICONST_4
    INVOKEVIRTUAL edu/utd/sonnv/Test.getArray$$PHOSPHORTAGGED (Ledu/columbia/cs/psl/phosphor/runtime/Taint;I)Ledu/columbia/cs/psl/phosphor/struct/LazyIntArrayObjTags;
    DUP
    IFNULL L4
    DUP
    GETFIELD edu/columbia/cs/psl/phosphor/struct/LazyIntArrayObjTags.val : [I
    GOTO L5
   L4
   FRAME FULL [edu/utd/sonnv/Test edu/columbia/cs/psl/phosphor/struct/TaintedIntWithObjTag] [edu/columbia/cs/psl/phosphor/struct/LazyIntArrayObjTags]
    ACONST_NULL
    CHECKCAST [I
   L5
   FRAME FULL [edu/utd/sonnv/Test edu/columbia/cs/psl/phosphor/struct/TaintedIntWithObjTag] [edu/columbia/cs/psl/phosphor/struct/LazyIntArrayObjTags [I]
   L6
    ASTORE 2
    ASTORE 3
   L7
    LINENUMBER 105 L7
    ALOAD 2
    IFNONNULL L8
   L9
    ACONST_NULL
    GOTO L10
   L11
   L8
   FRAME FULL [edu/utd/sonnv/Test edu/columbia/cs/psl/phosphor/struct/TaintedIntWithObjTag [I edu/columbia/cs/psl/phosphor/struct/LazyIntArrayObjTags] []
    ALOAD 3
    ALOAD 2
    ICONST_1
    ALOAD 1
    INVOKEVIRTUAL edu/columbia/cs/psl/phosphor/struct/LazyIntArrayObjTags.get ([IILedu/columbia/cs/psl/phosphor/struct/TaintedIntWithObjTag;)Ledu/columbia/cs/psl/phosphor/struct/TaintedIntWithObjTag;
    DUP
    GETFIELD edu/columbia/cs/psl/phosphor/struct/TaintedIntWithObjTag.taint : Ledu/columbia/cs/psl/phosphor/runtime/Taint;
    SWAP
    GETFIELD edu/columbia/cs/psl/phosphor/struct/TaintedIntWithObjTag.val : I
    SWAP
    DUP
    IFNONNULL L12
    SWAP
    INVOKESTATIC java/lang/Integer.valueOf$$PHOSPHORTAGGED (Ledu/columbia/cs/psl/phosphor/runtime/Taint;I)Ljava/lang/Integer;
    GOTO L13
   L12
   FRAME FULL [edu/utd/sonnv/Test edu/columbia/cs/psl/phosphor/struct/TaintedIntWithObjTag [I edu/columbia/cs/psl/phosphor/struct/LazyIntArrayObjTags] [I edu/columbia/cs/psl/phosphor/runtime/Taint]
    SWAP
   L14
    NEW java/lang/Integer
    DUP
    DUP2_X2
    POP2
    ACONST_NULL
    INVOKESPECIAL java/lang/Integer.<init> (Ledu/columbia/cs/psl/phosphor/runtime/Taint;ILedu/columbia/cs/psl/phosphor/runtime/TaintSentinel;)V
    DUP
    DUP
    GETFIELD java/lang/Integer.valuePHOSPHOR_TAG : I
    INVOKESTATIC edu/columbia/cs/psl/phosphor/runtime/HardcodedBypassStore.get (I)Ljava/lang/Object;
    CHECKCAST edu/columbia/cs/psl/phosphor/runtime/Taint
    INVOKEVIRTUAL java/lang/Integer.setPHOSPHOR_TAG (Ljava/lang/Object;)V
   L13
   L10
   FRAME FULL [edu/utd/sonnv/Test edu/columbia/cs/psl/phosphor/struct/TaintedIntWithObjTag [I edu/columbia/cs/psl/phosphor/struct/LazyIntArrayObjTags] [java/lang/Integer]
    ALOAD 1
    INVOKEVIRTUAL java/lang/Integer.intValue$$PHOSPHORTAGGED (Ledu/columbia/cs/psl/phosphor/struct/TaintedIntWithObjTag;)Ledu/columbia/cs/psl/phosphor/struct/TaintedIntWithObjTag;
    DUP
    GETFIELD edu/columbia/cs/psl/phosphor/struct/TaintedIntWithObjTag.taint : Ledu/columbia/cs/psl/phosphor/runtime/Taint;
    SWAP
    GETFIELD edu/columbia/cs/psl/phosphor/struct/TaintedIntWithObjTag.val : I
    LDC "edu.utd.sonnv.Test.testTernaryWithPrimitive"
    ALOAD 1
    INVOKESTATIC edu/columbia/cs/psl/phosphor/runtime/MultiTainter.taintedInt$$PHOSPHORTAGGED (Ledu/columbia/cs/psl/phosphor/runtime/Taint;ILjava/lang/Object;Ledu/columbia/cs/psl/phosphor/struct/TaintedIntWithObjTag;)Ledu/columbia/cs/psl/phosphor/struct/TaintedIntWithObjTag;
    DUP
    GETFIELD edu/columbia/cs/psl/phosphor/struct/TaintedIntWithObjTag.taint : Ledu/columbia/cs/psl/phosphor/runtime/Taint;
    SWAP
    GETFIELD edu/columbia/cs/psl/phosphor/struct/TaintedIntWithObjTag.val : I
    GETSTATIC java/lang/System.out : Ljava/io/PrintStream;
    LDC "Return: edu.utd.sonnv.Test.testTernaryWithPrimitive"
    INVOKEVIRTUAL java/io/PrintStream.println (Ljava/lang/String;)V
    ALOAD 1
    SWAP
    PUTFIELD edu/columbia/cs/psl/phosphor/struct/TaintedIntWithObjTag.val : I
    ALOAD 1
    SWAP
    PUTFIELD edu/columbia/cs/psl/phosphor/struct/TaintedIntWithObjTag.taint : Ledu/columbia/cs/psl/phosphor/runtime/Taint;
    ALOAD 1
    ARETURN
   L15
    LOCALVARIABLE this Ledu/utd/sonnv/Test; L3 L15 0
   L16
    LOCALVARIABLE phosphorShadowLVFor2XX0 Ledu/columbia/cs/psl/phosphor/struct/LazyIntArrayObjTags; L6 L16 3
    LOCALVARIABLE nameSet [I L7 L15 2
    MAXSTACK = 103
    MAXLOCALS = 4

  // access flags 0x1
  public testObjectConst$$PHOSPHORTAGGED(Ledu/columbia/cs/psl/phosphor/runtime/Taint;JLjava/lang/String;Ledu/columbia/cs/psl/phosphor/runtime/Taint;I)Ljava/lang/String;
   L0
   L1
   L2
    NEW edu/columbia/cs/psl/phosphor/struct/TaintedLongWithObjTag
    DUP
    INVOKESPECIAL edu/columbia/cs/psl/phosphor/struct/TaintedLongWithObjTag.<init> ()V
    ASTORE 7
   L3
    NEW edu/columbia/cs/psl/phosphor/struct/TaintedIntWithObjTag
    DUP
    INVOKESPECIAL edu/columbia/cs/psl/phosphor/struct/TaintedIntWithObjTag.<init> ()V
    ASTORE 8
   L4
    ALOAD 1
    LLOAD 2
    ACONST_NULL
    ALOAD 7
    INVOKESTATIC edu/columbia/cs/psl/phosphor/runtime/MultiTainter.taintedLong$$PHOSPHORTAGGED (Ledu/columbia/cs/psl/phosphor/runtime/Taint;ILjava/lang/Object;Ledu/columbia/cs/psl/phosphor/struct/TaintedLongWithObjTag;)Ledu/columbia/cs/psl/phosphor/struct/TaintedLongWithObjTag;
    GETFIELD edu/columbia/cs/psl/phosphor/struct/TaintedLongWithObjTag.val : J
    LSTORE 2
    ILOAD 4
    ACONST_NULL
    ALOAD 8
    INVOKESTATIC edu/columbia/cs/psl/phosphor/runtime/MultiTainter.taintedInt$$PHOSPHORTAGGED (Ledu/columbia/cs/psl/phosphor/runtime/Taint;ILjava/lang/Object;Ledu/columbia/cs/psl/phosphor/struct/TaintedIntWithObjTag;)Ledu/columbia/cs/psl/phosphor/struct/TaintedIntWithObjTag;
    GETFIELD edu/columbia/cs/psl/phosphor/struct/TaintedIntWithObjTag.val : I
    ISTORE 4
   L5
    LINENUMBER 109 L5
    ALOAD 4
    IFNONNULL L6
   L7
   L8
    LINENUMBER 110 L8
    LDC ""
    GETSTATIC java/lang/System.out : Ljava/io/PrintStream;
    LDC "Return object: edu.utd.sonnv.Test.testObjectConst"
    INVOKEVIRTUAL java/io/PrintStream.println (Ljava/lang/String;)V
    ARETURN
   L6
    LINENUMBER 112 L6
   FRAME FULL [edu/utd/sonnv/Test edu/columbia/cs/psl/phosphor/runtime/Taint J I edu/columbia/cs/psl/phosphor/runtime/Taint I edu/columbia/cs/psl/phosphor/struct/TaintedLongWithObjTag edu/columbia/cs/psl/phosphor/struct/TaintedIntWithObjTag] [J]
    LDC ""
    ASTORE 9
   L9
    LINENUMBER 113 L9
    ILOAD 6
    LOOKUPSWITCH
      1: L10
      2: L11
      default: L12
   L10
    LINENUMBER 115 L10
   FRAME FULL [edu/utd/sonnv/Test edu/columbia/cs/psl/phosphor/runtime/Taint J I edu/columbia/cs/psl/phosphor/runtime/Taint I edu/columbia/cs/psl/phosphor/struct/TaintedLongWithObjTag edu/columbia/cs/psl/phosphor/struct/TaintedIntWithObjTag java/lang/String] [J]
    ALOAD 0
    ALOAD 5
    ILOAD 6
    INVOKEVIRTUAL edu/utd/sonnv/Test.test5$$PHOSPHORTAGGED (Ledu/columbia/cs/psl/phosphor/runtime/Taint;I)Ljava/lang/String;
    ASTORE 2
    ALOAD 2
   L13
    NEW edu/columbia/cs/psl/phosphor/runtime/Taint
    DUP
    LDC "edu.utd.sonnv.Test.testObjectConst"
    INVOKESPECIAL edu/columbia/cs/psl/phosphor/runtime/Taint.<init> (Ljava/lang/Object;)V
    INVOKESTATIC edu/columbia/cs/psl/phosphor/runtime/MultiTainter.taintedObject (Ljava/lang/Object;Ledu/columbia/cs/psl/phosphor/runtime/Taint;)V
    ALOAD 2
    GETSTATIC java/lang/System.out : Ljava/io/PrintStream;
    LDC "Return object: edu.utd.sonnv.Test.testObjectConst"
    INVOKEVIRTUAL java/io/PrintStream.println (Ljava/lang/String;)V
    ARETURN
   L11
    LINENUMBER 117 L11
   FRAME FULL [edu/utd/sonnv/Test edu/columbia/cs/psl/phosphor/runtime/Taint J I edu/columbia/cs/psl/phosphor/runtime/Taint I edu/columbia/cs/psl/phosphor/struct/TaintedLongWithObjTag edu/columbia/cs/psl/phosphor/struct/TaintedIntWithObjTag java/lang/String] [J]
    ALOAD 0
   L14
    NEW java/lang/StringBuilder
    DUP
    INVOKESPECIAL java/lang/StringBuilder.<init> ()V
    LDC ""
    INVOKEVIRTUAL java/lang/StringBuilder.append (Ljava/lang/String;)Ljava/lang/StringBuilder;
    ALOAD 5
    ILOAD 6
    INVOKEVIRTUAL java/lang/StringBuilder.append$$PHOSPHORTAGGED (Ledu/columbia/cs/psl/phosphor/runtime/Taint;I)Ljava/lang/StringBuilder;
    INVOKEVIRTUAL java/lang/StringBuilder.toString ()Ljava/lang/String;
    INVOKEVIRTUAL edu/utd/sonnv/Test.testTernaryWithObject (Ljava/lang/String;)Ljava/lang/String;
    ASTORE 2
    ALOAD 2
   L15
    NEW edu/columbia/cs/psl/phosphor/runtime/Taint
    DUP
    LDC "edu.utd.sonnv.Test.testObjectConst"
    INVOKESPECIAL edu/columbia/cs/psl/phosphor/runtime/Taint.<init> (Ljava/lang/Object;)V
    INVOKESTATIC edu/columbia/cs/psl/phosphor/runtime/MultiTainter.taintedObject (Ljava/lang/Object;Ledu/columbia/cs/psl/phosphor/runtime/Taint;)V
    ALOAD 2
    GETSTATIC java/lang/System.out : Ljava/io/PrintStream;
    LDC "Return object: edu.utd.sonnv.Test.testObjectConst"
    INVOKEVIRTUAL java/io/PrintStream.println (Ljava/lang/String;)V
    ARETURN
   L12
    LINENUMBER 119 L12
   FRAME FULL [edu/utd/sonnv/Test edu/columbia/cs/psl/phosphor/runtime/Taint J I edu/columbia/cs/psl/phosphor/runtime/Taint I edu/columbia/cs/psl/phosphor/struct/TaintedLongWithObjTag edu/columbia/cs/psl/phosphor/struct/TaintedIntWithObjTag java/lang/String] [J]
    LDC ""
    GETSTATIC java/lang/System.out : Ljava/io/PrintStream;
    LDC "Return object: edu.utd.sonnv.Test.testObjectConst"
    INVOKEVIRTUAL java/io/PrintStream.println (Ljava/lang/String;)V
    ARETURN
   L16
    LOCALVARIABLE this Ledu/utd/sonnv/Test; L5 L16 0
   L17
    LOCALVARIABLE phosphorReturnPreAlloc0 Ledu/columbia/cs/psl/phosphor/struct/TaintedLongWithObjTag; L2 L17 7
    LOCALVARIABLE phosphorReturnPreAlloc1 Ledu/columbia/cs/psl/phosphor/struct/TaintedIntWithObjTag; L3 L17 8
    LOCALVARIABLE instant_TAINT Ledu/columbia/cs/psl/phosphor/runtime/Taint; L5 L16 1
    LOCALVARIABLE instant J L5 L16 2
    LOCALVARIABLE displayZone Ljava/lang/String; L5 L16 4
    LOCALVARIABLE i_TAINT Ledu/columbia/cs/psl/phosphor/runtime/Taint; L5 L16 5
    LOCALVARIABLE i I L5 L16 6
    LOCALVARIABLE x Ljava/lang/String; L9 L16 9
    MAXSTACK = 106
    MAXLOCALS = 10

  // access flags 0x1
  public testxxx$$PHOSPHORTAGGED(Ledu/columbia/cs/psl/phosphor/runtime/Taint;ILedu/columbia/cs/psl/phosphor/struct/LazyDoubleArrayObjTags;[DLedu/columbia/cs/psl/phosphor/runtime/Taint;J)V
   L0
   L1
   L2
    NEW edu/columbia/cs/psl/phosphor/struct/TaintedLongWithObjTag
    DUP
    INVOKESPECIAL edu/columbia/cs/psl/phosphor/struct/TaintedLongWithObjTag.<init> ()V
    ASTORE 8
   L3
    NEW edu/columbia/cs/psl/phosphor/struct/TaintedIntWithObjTag
    DUP
    INVOKESPECIAL edu/columbia/cs/psl/phosphor/struct/TaintedIntWithObjTag.<init> ()V
    ASTORE 9
   L4
    ALOAD 1
    ILOAD 2
    ACONST_NULL
    ALOAD 9
    INVOKESTATIC edu/columbia/cs/psl/phosphor/runtime/MultiTainter.taintedInt$$PHOSPHORTAGGED (Ledu/columbia/cs/psl/phosphor/runtime/Taint;ILjava/lang/Object;Ledu/columbia/cs/psl/phosphor/struct/TaintedIntWithObjTag;)Ledu/columbia/cs/psl/phosphor/struct/TaintedIntWithObjTag;
    GETFIELD edu/columbia/cs/psl/phosphor/struct/TaintedIntWithObjTag.val : I
    ISTORE 2
    ALOAD 5
    LLOAD 6
    ACONST_NULL
    ALOAD 8
    INVOKESTATIC edu/columbia/cs/psl/phosphor/runtime/MultiTainter.taintedLong$$PHOSPHORTAGGED (Ledu/columbia/cs/psl/phosphor/runtime/Taint;ILjava/lang/Object;Ledu/columbia/cs/psl/phosphor/struct/TaintedLongWithObjTag;)Ledu/columbia/cs/psl/phosphor/struct/TaintedLongWithObjTag;
    GETFIELD edu/columbia/cs/psl/phosphor/struct/TaintedLongWithObjTag.val : J
    LSTORE 6
   L5
    LINENUMBER 124 L5
    GETSTATIC java/lang/System.out : Ljava/io/PrintStream;
    LDC "Void: edu.utd.sonnv.Test.testxxx"
    INVOKEVIRTUAL java/io/PrintStream.println (Ljava/lang/String;)V
    RETURN
   L6
    LOCALVARIABLE this Ledu/utd/sonnv/Test; L5 L6 0
   L7
    LOCALVARIABLE phosphorReturnPreAlloc0 Ledu/columbia/cs/psl/phosphor/struct/TaintedLongWithObjTag; L2 L7 8
    LOCALVARIABLE phosphorReturnPreAlloc1 Ledu/columbia/cs/psl/phosphor/struct/TaintedIntWithObjTag; L3 L7 9
    LOCALVARIABLE x_TAINT Ledu/columbia/cs/psl/phosphor/runtime/Taint; L5 L6 1
    LOCALVARIABLE x I L5 L6 2
    LOCALVARIABLE y_TAINT Ledu/columbia/cs/psl/phosphor/struct/LazyDoubleArrayObjTags; L5 L6 3
    LOCALVARIABLE y [D L5 L6 4
    LOCALVARIABLE z_TAINT Ledu/columbia/cs/psl/phosphor/runtime/Taint; L5 L6 5
    LOCALVARIABLE z J L5 L6 6
    MAXSTACK = 103
    MAXLOCALS = 10

  // access flags 0x1
  public testxxx$$PHOSPHORTAGGED(Ledu/columbia/cs/psl/phosphor/runtime/Taint;ILedu/columbia/cs/psl/phosphor/struct/LazyIntArrayObjTags;[ILedu/columbia/cs/psl/phosphor/runtime/Taint;DLedu/utd/sonnv/Test$TestX;Ledu/utd/sonnv/Test$TestX;Ledu/columbia/cs/psl/phosphor/struct/LazyLongArrayObjTags;[J)V
   L0
   L1
   L2
    NEW edu/columbia/cs/psl/phosphor/struct/TaintedDoubleWithObjTag
    DUP
    INVOKESPECIAL edu/columbia/cs/psl/phosphor/struct/TaintedDoubleWithObjTag.<init> ()V
    ASTORE 12
   L3
    NEW edu/columbia/cs/psl/phosphor/struct/TaintedIntWithObjTag
    DUP
    INVOKESPECIAL edu/columbia/cs/psl/phosphor/struct/TaintedIntWithObjTag.<init> ()V
    ASTORE 13
   L4
    ALOAD 1
    ILOAD 2
    ACONST_NULL
    ALOAD 13
    INVOKESTATIC edu/columbia/cs/psl/phosphor/runtime/MultiTainter.taintedInt$$PHOSPHORTAGGED (Ledu/columbia/cs/psl/phosphor/runtime/Taint;ILjava/lang/Object;Ledu/columbia/cs/psl/phosphor/struct/TaintedIntWithObjTag;)Ledu/columbia/cs/psl/phosphor/struct/TaintedIntWithObjTag;
    GETFIELD edu/columbia/cs/psl/phosphor/struct/TaintedIntWithObjTag.val : I
    ISTORE 2
    ALOAD 5
    DLOAD 6
    ACONST_NULL
    ALOAD 12
    INVOKESTATIC edu/columbia/cs/psl/phosphor/runtime/MultiTainter.taintedDouble$$PHOSPHORTAGGED (Ledu/columbia/cs/psl/phosphor/runtime/Taint;ILjava/lang/Object;Ledu/columbia/cs/psl/phosphor/struct/TaintedDoubleWithObjTag;)Ledu/columbia/cs/psl/phosphor/struct/TaintedDoubleWithObjTag;
    GETFIELD edu/columbia/cs/psl/phosphor/struct/TaintedDoubleWithObjTag.val : D
    DSTORE 6
   L5
    LINENUMBER 128 L5
    GETSTATIC java/lang/System.out : Ljava/io/PrintStream;
    LDC "Void: edu.utd.sonnv.Test.testxxx"
    INVOKEVIRTUAL java/io/PrintStream.println (Ljava/lang/String;)V
    RETURN
   L6
    LOCALVARIABLE this Ledu/utd/sonnv/Test; L5 L6 0
   L7
    LOCALVARIABLE phosphorReturnPreAlloc0 Ledu/columbia/cs/psl/phosphor/struct/TaintedDoubleWithObjTag; L2 L7 12
    LOCALVARIABLE phosphorReturnPreAlloc1 Ledu/columbia/cs/psl/phosphor/struct/TaintedIntWithObjTag; L3 L7 13
    LOCALVARIABLE u_TAINT Ledu/columbia/cs/psl/phosphor/runtime/Taint; L5 L6 1
    LOCALVARIABLE u I L5 L6 2
    LOCALVARIABLE t_TAINT Ledu/columbia/cs/psl/phosphor/struct/LazyIntArrayObjTags; L5 L6 3
    LOCALVARIABLE t [I L5 L6 4
    LOCALVARIABLE kx_TAINT Ledu/columbia/cs/psl/phosphor/runtime/Taint; L5 L6 5
    LOCALVARIABLE kx D L5 L6 6
    LOCALVARIABLE x Ledu/utd/sonnv/Test$TestX; L5 L6 8
    LOCALVARIABLE k Ledu/utd/sonnv/Test$TestX; L5 L6 9
    LOCALVARIABLE z_TAINT Ledu/columbia/cs/psl/phosphor/struct/LazyLongArrayObjTags; L5 L6 10
    LOCALVARIABLE z [J L5 L6 11
    MAXSTACK = 103
    MAXLOCALS = 14

  // access flags 0x9
  public static main([Ljava/lang/String;)V
   L0
   L1
   L2
    NEW edu/columbia/cs/psl/phosphor/struct/TaintedIntWithObjTag
    DUP
    INVOKESPECIAL edu/columbia/cs/psl/phosphor/struct/TaintedIntWithObjTag.<init> ()V
    ASTORE 1
   L3
   L4
    LINENUMBER 131 L4
    NEW edu/utd/sonnv/Test
    DUP
    INVOKESPECIAL edu/utd/sonnv/Test.<init> ()V
    ASTORE 2
   L5
    LINENUMBER 132 L5
    ALOAD 2
    ACONST_NULL
    ICONST_1
    ACONST_NULL
    ICONST_2
    ALOAD 1
    INVOKEVIRTUAL edu/utd/sonnv/Test.testNomalCase$$PHOSPHORTAGGED (Ledu/columbia/cs/psl/phosphor/runtime/Taint;ILedu/columbia/cs/psl/phosphor/runtime/Taint;ILedu/columbia/cs/psl/phosphor/struct/TaintedIntWithObjTag;)Ledu/columbia/cs/psl/phosphor/struct/TaintedIntWithObjTag;
    GETFIELD edu/columbia/cs/psl/phosphor/struct/TaintedIntWithObjTag.val : I
    ISTORE 3
   L6
    LINENUMBER 146 L6
    GETSTATIC java/lang/System.out : Ljava/io/PrintStream;
    LDC "Void: edu.utd.sonnv.Test.main"
    INVOKEVIRTUAL java/io/PrintStream.println (Ljava/lang/String;)V
    RETURN
   L7
    LOCALVARIABLE args [Ljava/lang/String; L4 L7 0
   L8
    LOCALVARIABLE phosphorReturnPreAlloc0 Ledu/columbia/cs/psl/phosphor/struct/TaintedIntWithObjTag; L2 L8 1
    LOCALVARIABLE test Ledu/utd/sonnv/Test; L5 L7 2
    LOCALVARIABLE result I L6 L7 3
    MAXSTACK = 103
    MAXLOCALS = 4

  // access flags 0x1
  public castting(Ljava/lang/Object;)Ledu/utd/sonnv/Test$TestX;
   L0
   L1
   L2
   L3
    LINENUMBER 149 L3
    ALOAD 1
    INSTANCEOF edu/utd/sonnv/Test$TestX
    IFEQ L4
   L5
   L6
    LINENUMBER 150 L6
    ALOAD 1
    CHECKCAST edu/utd/sonnv/Test$TestX
    GETSTATIC java/lang/System.out : Ljava/io/PrintStream;
    LDC "Return object: edu.utd.sonnv.Test.castting"
    INVOKEVIRTUAL java/io/PrintStream.println (Ljava/lang/String;)V
    ARETURN
   L4
    LINENUMBER 152 L4
   FRAME FULL [edu/utd/sonnv/Test java/lang/Object] []
    NEW edu/utd/sonnv/Test$TestX
    DUP
    INVOKESPECIAL edu/utd/sonnv/Test$TestX.<init> ()V
    GETSTATIC java/lang/System.out : Ljava/io/PrintStream;
    LDC "Return object: edu.utd.sonnv.Test.castting"
    INVOKEVIRTUAL java/io/PrintStream.println (Ljava/lang/String;)V
    ARETURN
   L7
    LOCALVARIABLE this Ledu/utd/sonnv/Test; L3 L7 0
    LOCALVARIABLE a Ljava/lang/Object; L3 L7 1
   L8
    MAXSTACK = 103
    MAXLOCALS = 2

  // access flags 0x1
  public castting()Ledu/utd/sonnv/Test$TestX;
   L0
   L1
   L2
   L3
    LINENUMBER 156 L3
    NEW edu/utd/sonnv/Test$TestX
    DUP
    INVOKESPECIAL edu/utd/sonnv/Test$TestX.<init> ()V
    GETSTATIC java/lang/System.out : Ljava/io/PrintStream;
    LDC "Return object: edu.utd.sonnv.Test.castting"
    INVOKEVIRTUAL java/io/PrintStream.println (Ljava/lang/String;)V
    ARETURN
   L4
    LOCALVARIABLE this Ledu/utd/sonnv/Test; L3 L4 0
   L5
    MAXSTACK = 103
    MAXLOCALS = 1

  // access flags 0x18
  final static J serialVersionUID = -2576914290537339177

  // access flags 0x1
  public Ledu/columbia/cs/psl/phosphor/runtime/Taint; PHOSPHOR_TAG

  // access flags 0x9
  public static Ledu/columbia/cs/psl/phosphor/runtime/Taint; serialVersionUIDPHOSPHOR_TAG

  // access flags 0x1
  public equals(Ljava/lang/Object;)Z
   L0
    ALOAD 0
    ALOAD 1
    INVOKESPECIAL java/lang/Object.equals (Ljava/lang/Object;)Z
   L1
    IRETURN
    LOCALVARIABLE this Ledu/utd/sonnv/Test; L0 L1 0
    LOCALVARIABLE other Ljava/lang/Object; L0 L1 1
    MAXSTACK = 0
    MAXLOCALS = 0

  // access flags 0x1
  public hashCode()I
   L0
    ALOAD 0
    INVOKESPECIAL java/lang/Object.hashCode ()I
   L1
    IRETURN
    LOCALVARIABLE this Ledu/utd/sonnv/Test; L0 L1 0
    MAXSTACK = 0
    MAXLOCALS = 0

  // access flags 0x1
  public getPHOSPHOR_TAG()Ljava/lang/Object;
    ALOAD 0
    GETFIELD edu/utd/sonnv/Test.PHOSPHOR_TAG : Ledu/columbia/cs/psl/phosphor/runtime/Taint;
    ARETURN
    MAXSTACK = 0
    MAXLOCALS = 0

  // access flags 0x1
  public setPHOSPHOR_TAG(Ljava/lang/Object;)V
    ALOAD 0
    ALOAD 1
    CHECKCAST edu/columbia/cs/psl/phosphor/runtime/Taint
    PUTFIELD edu/utd/sonnv/Test.PHOSPHOR_TAG : Ledu/columbia/cs/psl/phosphor/runtime/Taint;
    RETURN
    MAXSTACK = 0
    MAXLOCALS = 0

  // access flags 0x1
  public test5(I)Ljava/lang/String;
   L0
   L1
    LINENUMBER 0 L1
    ALOAD 0
    ACONST_NULL
    ILOAD 1
    INVOKESPECIAL edu/utd/sonnv/Test.test5$$PHOSPHORTAGGED (Ledu/columbia/cs/psl/phosphor/runtime/Taint;I)Ljava/lang/String;
   L2
    ARETURN
    LOCALVARIABLE this Ledu/utd/sonnv/Test; L1 L2 0
    LOCALVARIABLE x I L1 L2 1
   L3
    MAXSTACK = 3
    MAXLOCALS = 2

  // access flags 0x1
  public testObj1(I)Ljava/lang/String;
   L0
   L1
    LINENUMBER 0 L1
    ALOAD 0
    ACONST_NULL
    ILOAD 1
    INVOKESPECIAL edu/utd/sonnv/Test.testObj1$$PHOSPHORTAGGED (Ledu/columbia/cs/psl/phosphor/runtime/Taint;I)Ljava/lang/String;
   L2
    ARETURN
    LOCALVARIABLE this Ledu/utd/sonnv/Test; L1 L2 0
    LOCALVARIABLE x I L1 L2 1
   L3
    MAXSTACK = 3
    MAXLOCALS = 2

  // access flags 0x1
  public testSwitchCase(I)Ljava/lang/String;
   L0
   L1
    LINENUMBER 0 L1
    ALOAD 0
    ACONST_NULL
    ILOAD 1
    INVOKESPECIAL edu/utd/sonnv/Test.testSwitchCase$$PHOSPHORTAGGED (Ledu/columbia/cs/psl/phosphor/runtime/Taint;I)Ljava/lang/String;
   L2
    ARETURN
    LOCALVARIABLE this Ledu/utd/sonnv/Test; L1 L2 0
    LOCALVARIABLE x I L1 L2 1
   L3
    MAXSTACK = 3
    MAXLOCALS = 2

  // access flags 0x1
  public testNomalCase(II)I
   L0
   L1
    NEW edu/columbia/cs/psl/phosphor/struct/TaintedIntWithObjTag
    DUP
    INVOKESPECIAL edu/columbia/cs/psl/phosphor/struct/TaintedIntWithObjTag.<init> ()V
    ASTORE 3
   L2
    LINENUMBER 0 L2
    ALOAD 0
    ACONST_NULL
    ILOAD 1
    ACONST_NULL
    ILOAD 2
    ALOAD 3
    INVOKESPECIAL edu/utd/sonnv/Test.testNomalCase$$PHOSPHORTAGGED (Ledu/columbia/cs/psl/phosphor/runtime/Taint;ILedu/columbia/cs/psl/phosphor/runtime/Taint;ILedu/columbia/cs/psl/phosphor/struct/TaintedIntWithObjTag;)Ledu/columbia/cs/psl/phosphor/struct/TaintedIntWithObjTag;
    GETFIELD edu/columbia/cs/psl/phosphor/struct/TaintedIntWithObjTag.val : I
   L3
    IRETURN
    LOCALVARIABLE this Ledu/utd/sonnv/Test; L2 L3 0
   L4
    LOCALVARIABLE phosphorReturnPreAlloc0 Ledu/columbia/cs/psl/phosphor/struct/TaintedIntWithObjTag; L1 L4 3
    LOCALVARIABLE input1 I L2 L3 1
    LOCALVARIABLE input2 I L2 L3 2
    MAXSTACK = 6
    MAXLOCALS = 4

  // access flags 0x1
  public testArrayUsage(I)I
   L0
   L1
    NEW edu/columbia/cs/psl/phosphor/struct/TaintedIntWithObjTag
    DUP
    INVOKESPECIAL edu/columbia/cs/psl/phosphor/struct/TaintedIntWithObjTag.<init> ()V
    ASTORE 2
   L2
    LINENUMBER 0 L2
    ALOAD 0
    ACONST_NULL
    ILOAD 1
    ALOAD 2
    INVOKESPECIAL edu/utd/sonnv/Test.testArrayUsage$$PHOSPHORTAGGED (Ledu/columbia/cs/psl/phosphor/runtime/Taint;ILedu/columbia/cs/psl/phosphor/struct/TaintedIntWithObjTag;)Ledu/columbia/cs/psl/phosphor/struct/TaintedIntWithObjTag;
    GETFIELD edu/columbia/cs/psl/phosphor/struct/TaintedIntWithObjTag.val : I
   L3
    IRETURN
    LOCALVARIABLE this Ledu/utd/sonnv/Test; L2 L3 0
   L4
    LOCALVARIABLE phosphorReturnPreAlloc0 Ledu/columbia/cs/psl/phosphor/struct/TaintedIntWithObjTag; L1 L4 2
    LOCALVARIABLE x I L2 L3 1
    MAXSTACK = 4
    MAXLOCALS = 3

  // access flags 0x1
  public getArray(I)[I
   L0
   L1
    LINENUMBER 0 L1
    ALOAD 0
    ACONST_NULL
    ILOAD 1
    INVOKESPECIAL edu/utd/sonnv/Test.getArray$$PHOSPHORTAGGED (Ledu/columbia/cs/psl/phosphor/runtime/Taint;I)Ledu/columbia/cs/psl/phosphor/struct/LazyIntArrayObjTags;
    DUP
    IFNULL L2
    GETFIELD edu/columbia/cs/psl/phosphor/struct/LazyIntArrayObjTags.val : [I
    GOTO L3
   L2
   FRAME FULL [edu/utd/sonnv/Test I] [edu/columbia/cs/psl/phosphor/struct/LazyIntArrayObjTags]
    POP
    ACONST_NULL
   L3
   FRAME FULL [edu/utd/sonnv/Test I] [[I]
   L4
    ARETURN
    LOCALVARIABLE this Ledu/utd/sonnv/Test; L1 L4 0
    LOCALVARIABLE x I L1 L4 1
   L5
    MAXSTACK = 3
    MAXLOCALS = 2

  // access flags 0x1
  public getCastingValue(I)I
   L0
   L1
    NEW edu/columbia/cs/psl/phosphor/struct/TaintedIntWithObjTag
    DUP
    INVOKESPECIAL edu/columbia/cs/psl/phosphor/struct/TaintedIntWithObjTag.<init> ()V
    ASTORE 2
   L2
    LINENUMBER 0 L2
    ALOAD 0
    ACONST_NULL
    ILOAD 1
    ALOAD 2
    INVOKESPECIAL edu/utd/sonnv/Test.getCastingValue$$PHOSPHORTAGGED (Ledu/columbia/cs/psl/phosphor/runtime/Taint;ILedu/columbia/cs/psl/phosphor/struct/TaintedIntWithObjTag;)Ledu/columbia/cs/psl/phosphor/struct/TaintedIntWithObjTag;
    GETFIELD edu/columbia/cs/psl/phosphor/struct/TaintedIntWithObjTag.val : I
   L3
    IRETURN
    LOCALVARIABLE this Ledu/utd/sonnv/Test; L2 L3 0
   L4
    LOCALVARIABLE phosphorReturnPreAlloc0 Ledu/columbia/cs/psl/phosphor/struct/TaintedIntWithObjTag; L1 L4 2
    LOCALVARIABLE x I L2 L3 1
    MAXSTACK = 4
    MAXLOCALS = 3

  // access flags 0x1
  public getNormalValue(I)I
   L0
   L1
    NEW edu/columbia/cs/psl/phosphor/struct/TaintedIntWithObjTag
    DUP
    INVOKESPECIAL edu/columbia/cs/psl/phosphor/struct/TaintedIntWithObjTag.<init> ()V
    ASTORE 2
   L2
    LINENUMBER 0 L2
    ALOAD 0
    ACONST_NULL
    ILOAD 1
    ALOAD 2
    INVOKESPECIAL edu/utd/sonnv/Test.getNormalValue$$PHOSPHORTAGGED (Ledu/columbia/cs/psl/phosphor/runtime/Taint;ILedu/columbia/cs/psl/phosphor/struct/TaintedIntWithObjTag;)Ledu/columbia/cs/psl/phosphor/struct/TaintedIntWithObjTag;
    GETFIELD edu/columbia/cs/psl/phosphor/struct/TaintedIntWithObjTag.val : I
   L3
    IRETURN
    LOCALVARIABLE this Ledu/utd/sonnv/Test; L2 L3 0
   L4
    LOCALVARIABLE phosphorReturnPreAlloc0 Ledu/columbia/cs/psl/phosphor/struct/TaintedIntWithObjTag; L1 L4 2
    LOCALVARIABLE x I L2 L3 1
    MAXSTACK = 4
    MAXLOCALS = 3

  // access flags 0x1
  public getReturnPrimitiveConst(I)I
   L0
   L1
    NEW edu/columbia/cs/psl/phosphor/struct/TaintedIntWithObjTag
    DUP
    INVOKESPECIAL edu/columbia/cs/psl/phosphor/struct/TaintedIntWithObjTag.<init> ()V
    ASTORE 2
   L2
    LINENUMBER 0 L2
    ALOAD 0
    ACONST_NULL
    ILOAD 1
    ALOAD 2
    INVOKESPECIAL edu/utd/sonnv/Test.getReturnPrimitiveConst$$PHOSPHORTAGGED (Ledu/columbia/cs/psl/phosphor/runtime/Taint;ILedu/columbia/cs/psl/phosphor/struct/TaintedIntWithObjTag;)Ledu/columbia/cs/psl/phosphor/struct/TaintedIntWithObjTag;
    GETFIELD edu/columbia/cs/psl/phosphor/struct/TaintedIntWithObjTag.val : I
   L3
    IRETURN
    LOCALVARIABLE this Ledu/utd/sonnv/Test; L2 L3 0
   L4
    LOCALVARIABLE phosphorReturnPreAlloc0 Ledu/columbia/cs/psl/phosphor/struct/TaintedIntWithObjTag; L1 L4 2
    LOCALVARIABLE x I L2 L3 1
    MAXSTACK = 4
    MAXLOCALS = 3

  // access flags 0x1
  public getValue4(I)S
   L0
   L1
    NEW edu/columbia/cs/psl/phosphor/struct/TaintedShortWithObjTag
    DUP
    INVOKESPECIAL edu/columbia/cs/psl/phosphor/struct/TaintedShortWithObjTag.<init> ()V
    ASTORE 2
   L2
    LINENUMBER 0 L2
    ALOAD 0
    ACONST_NULL
    ILOAD 1
    ALOAD 2
    INVOKESPECIAL edu/utd/sonnv/Test.getValue4$$PHOSPHORTAGGED (Ledu/columbia/cs/psl/phosphor/runtime/Taint;ILedu/columbia/cs/psl/phosphor/struct/TaintedShortWithObjTag;)Ledu/columbia/cs/psl/phosphor/struct/TaintedShortWithObjTag;
    GETFIELD edu/columbia/cs/psl/phosphor/struct/TaintedShortWithObjTag.val : S
   L3
    IRETURN
    LOCALVARIABLE this Ledu/utd/sonnv/Test; L2 L3 0
   L4
    LOCALVARIABLE phosphorReturnPreAlloc0 Ledu/columbia/cs/psl/phosphor/struct/TaintedShortWithObjTag; L1 L4 2
    LOCALVARIABLE x I L2 L3 1
    MAXSTACK = 4
    MAXLOCALS = 3

  // access flags 0x1
  public testTernaryWithPrimitive()I
   L0
   L1
    NEW edu/columbia/cs/psl/phosphor/struct/TaintedIntWithObjTag
    DUP
    INVOKESPECIAL edu/columbia/cs/psl/phosphor/struct/TaintedIntWithObjTag.<init> ()V
    ASTORE 1
   L2
    LINENUMBER 0 L2
    ALOAD 0
    ALOAD 1
    INVOKESPECIAL edu/utd/sonnv/Test.testTernaryWithPrimitive$$PHOSPHORTAGGED (Ledu/columbia/cs/psl/phosphor/struct/TaintedIntWithObjTag;)Ledu/columbia/cs/psl/phosphor/struct/TaintedIntWithObjTag;
    GETFIELD edu/columbia/cs/psl/phosphor/struct/TaintedIntWithObjTag.val : I
   L3
    IRETURN
    LOCALVARIABLE this Ledu/utd/sonnv/Test; L2 L3 0
   L4
    LOCALVARIABLE phosphorReturnPreAlloc0 Ledu/columbia/cs/psl/phosphor/struct/TaintedIntWithObjTag; L1 L4 1
    MAXSTACK = 2
    MAXLOCALS = 2

  // access flags 0x1
  public testObjectConst(JLjava/lang/String;I)Ljava/lang/String;
   L0
   L1
    LINENUMBER 0 L1
    ALOAD 0
    ACONST_NULL
    LLOAD 1
    ALOAD 3
    ACONST_NULL
    ILOAD 4
    INVOKESPECIAL edu/utd/sonnv/Test.testObjectConst$$PHOSPHORTAGGED (Ledu/columbia/cs/psl/phosphor/runtime/Taint;JLjava/lang/String;Ledu/columbia/cs/psl/phosphor/runtime/Taint;I)Ljava/lang/String;
   L2
    ARETURN
    LOCALVARIABLE this Ledu/utd/sonnv/Test; L1 L2 0
    LOCALVARIABLE instant J L1 L2 1
    LOCALVARIABLE displayZone Ljava/lang/String; L1 L2 3
    LOCALVARIABLE i I L1 L2 4
   L3
    MAXSTACK = 7
    MAXLOCALS = 5

  // access flags 0x1
  public testxxx(I[DJ)V
   L0
   L1
    LINENUMBER 0 L1
    ALOAD 0
    ACONST_NULL
    ILOAD 1
    ALOAD 2
    DUP
    IFNULL L2
    DUP
   L3
    NEW edu/columbia/cs/psl/phosphor/struct/LazyDoubleArrayObjTags
    DUP_X1
    SWAP
    INVOKESPECIAL edu/columbia/cs/psl/phosphor/struct/LazyDoubleArrayObjTags.<init> ([D)V
    SWAP
    GOTO L4
   FRAME FULL [edu/utd/sonnv/Test I [D J] [edu/utd/sonnv/Test N I [D]
   L2
    ACONST_NULL
    SWAP
   L4
   FRAME FULL [edu/utd/sonnv/Test I [D J] [edu/utd/sonnv/Test N I edu/columbia/cs/psl/phosphor/struct/LazyDoubleArrayObjTags [D]
    ACONST_NULL
    LLOAD 3
    INVOKESPECIAL edu/utd/sonnv/Test.testxxx$$PHOSPHORTAGGED (Ledu/columbia/cs/psl/phosphor/runtime/Taint;ILedu/columbia/cs/psl/phosphor/struct/LazyDoubleArrayObjTags;[DLedu/columbia/cs/psl/phosphor/runtime/Taint;J)V
   L5
    RETURN
    LOCALVARIABLE this Ledu/utd/sonnv/Test; L1 L5 0
    LOCALVARIABLE x I L1 L5 1
    LOCALVARIABLE y [D L1 L5 2
    LOCALVARIABLE z J L1 L5 3
   L6
    MAXSTACK = 8
    MAXLOCALS = 5

  // access flags 0x1
  public testxxx(I[IDLedu/utd/sonnv/Test$TestX;Ledu/utd/sonnv/Test$TestX;[J)V
   L0
   L1
    LINENUMBER 0 L1
    ALOAD 0
    ACONST_NULL
    ILOAD 1
    ALOAD 2
    DUP
    IFNULL L2
    DUP
   L3
    NEW edu/columbia/cs/psl/phosphor/struct/LazyIntArrayObjTags
    DUP_X1
    SWAP
    INVOKESPECIAL edu/columbia/cs/psl/phosphor/struct/LazyIntArrayObjTags.<init> ([I)V
    SWAP
    GOTO L4
   FRAME FULL [edu/utd/sonnv/Test I [I D edu/utd/sonnv/Test$TestX edu/utd/sonnv/Test$TestX [J] [edu/utd/sonnv/Test N I [I]
   L2
    ACONST_NULL
    SWAP
   L4
   FRAME FULL [edu/utd/sonnv/Test I [I D edu/utd/sonnv/Test$TestX edu/utd/sonnv/Test$TestX [J] [edu/utd/sonnv/Test N I edu/columbia/cs/psl/phosphor/struct/LazyIntArrayObjTags [I]
    ACONST_NULL
    DLOAD 3
    ALOAD 5
    ALOAD 6
    ALOAD 7
    DUP
    IFNULL L5
    DUP
   L6
    NEW edu/columbia/cs/psl/phosphor/struct/LazyLongArrayObjTags
    DUP_X1
    SWAP
    INVOKESPECIAL edu/columbia/cs/psl/phosphor/struct/LazyLongArrayObjTags.<init> ([J)V
    SWAP
    GOTO L7
   FRAME FULL [edu/utd/sonnv/Test I [I D edu/utd/sonnv/Test$TestX edu/utd/sonnv/Test$TestX [J] [edu/utd/sonnv/Test N I edu/columbia/cs/psl/phosphor/struct/LazyIntArrayObjTags [I N D edu/utd/sonnv/Test$TestX edu/utd/sonnv/Test$TestX [J]
   L5
    ACONST_NULL
    SWAP
   L7
   FRAME FULL [edu/utd/sonnv/Test I [I D edu/utd/sonnv/Test$TestX edu/utd/sonnv/Test$TestX [J] [edu/utd/sonnv/Test N I edu/columbia/cs/psl/phosphor/struct/LazyIntArrayObjTags [I N D edu/utd/sonnv/Test$TestX edu/utd/sonnv/Test$TestX edu/columbia/cs/psl/phosphor/struct/LazyLongArrayObjTags [J]
    INVOKESPECIAL edu/utd/sonnv/Test.testxxx$$PHOSPHORTAGGED (Ledu/columbia/cs/psl/phosphor/runtime/Taint;ILedu/columbia/cs/psl/phosphor/struct/LazyIntArrayObjTags;[ILedu/columbia/cs/psl/phosphor/runtime/Taint;DLedu/utd/sonnv/Test$TestX;Ledu/utd/sonnv/Test$TestX;Ledu/columbia/cs/psl/phosphor/struct/LazyLongArrayObjTags;[J)V
   L8
    RETURN
    LOCALVARIABLE this Ledu/utd/sonnv/Test; L1 L8 0
    LOCALVARIABLE u I L1 L8 1
    LOCALVARIABLE t [I L1 L8 2
    LOCALVARIABLE kx D L1 L8 3
    LOCALVARIABLE x Ledu/utd/sonnv/Test$TestX; L1 L8 5
    LOCALVARIABLE k Ledu/utd/sonnv/Test$TestX; L1 L8 6
    LOCALVARIABLE z [J L1 L8 7
   L9
    MAXSTACK = 14
    MAXLOCALS = 8

  // access flags 0x1
  public equals$$PHOSPHORTAGGED(Ljava/lang/Object;Ledu/columbia/cs/psl/phosphor/struct/TaintedBooleanWithObjTag;)Ledu/columbia/cs/psl/phosphor/struct/TaintedBooleanWithObjTag;
   L0
   L1
    ALOAD 0
    ALOAD 1
    DUP
    DUP
    INSTANCEOF [Ledu/columbia/cs/psl/phosphor/struct/LazyArrayObjTags;
    SWAP
    INSTANCEOF edu/columbia/cs/psl/phosphor/struct/LazyArrayObjTags
    IOR
    IFEQ L2
    INVOKESTATIC edu/columbia/cs/psl/phosphor/struct/multid/MultiDTaintedArrayWithObjTag.unboxRaw (Ljava/lang/Object;)Ljava/lang/Object;
   L2
   FRAME FULL [edu/utd/sonnv/Test java/lang/Object edu/columbia/cs/psl/phosphor/struct/TaintedBooleanWithObjTag] [edu/utd/sonnv/Test java/lang/Object]
    INVOKESPECIAL edu/utd/sonnv/Test.equals (Ljava/lang/Object;)Z
    ALOAD 2
    SWAP
    PUTFIELD edu/columbia/cs/psl/phosphor/struct/TaintedBooleanWithObjTag.val : Z
    ALOAD 2
    ACONST_NULL
    PUTFIELD edu/columbia/cs/psl/phosphor/struct/TaintedBooleanWithObjTag.taint : Ledu/columbia/cs/psl/phosphor/runtime/Taint;
    ALOAD 2
   L3
    ARETURN
    LOCALVARIABLE this Ledu/utd/sonnv/Test; L1 L3 0
    LOCALVARIABLE phosphorNativeWrapArg1 Ljava/lang/Object; L1 L3 1
    LOCALVARIABLE phosphorReturnHolder Ledu/columbia/cs/psl/phosphor/struct/TaintedBooleanWithObjTag; L1 L3 2
   L4
    MAXSTACK = 4
    MAXLOCALS = 3

  // access flags 0x1
  public hashCode$$PHOSPHORTAGGED(Ledu/columbia/cs/psl/phosphor/struct/TaintedIntWithObjTag;)Ledu/columbia/cs/psl/phosphor/struct/TaintedIntWithObjTag;
   L0
   L1
    ALOAD 0
    INVOKESPECIAL edu/utd/sonnv/Test.hashCode ()I
    ALOAD 1
    SWAP
    PUTFIELD edu/columbia/cs/psl/phosphor/struct/TaintedIntWithObjTag.val : I
    ALOAD 1
    ACONST_NULL
    PUTFIELD edu/columbia/cs/psl/phosphor/struct/TaintedIntWithObjTag.taint : Ledu/columbia/cs/psl/phosphor/runtime/Taint;
    ALOAD 1
   L2
    ARETURN
    LOCALVARIABLE this Ledu/utd/sonnv/Test; L1 L2 0
    LOCALVARIABLE phosphorReturnHolder Ledu/columbia/cs/psl/phosphor/struct/TaintedIntWithObjTag; L1 L2 1
   L3
    MAXSTACK = 2
    MAXLOCALS = 2

  // access flags 0x1
  public getClass$$PHOSPHORTAGGED()Ljava/lang/Class;
   L0
   L1
    ALOAD 0
    INVOKESPECIAL edu/utd/sonnv/Test.getClass ()Ljava/lang/Class;
   L2
    ARETURN
    LOCALVARIABLE this Ledu/utd/sonnv/Test; L1 L2 0
   L3
    MAXSTACK = 1
    MAXLOCALS = 1

  // access flags 0x1
  public toString$$PHOSPHORTAGGED()Ljava/lang/String;
   L0
   L1
    ALOAD 0
    INVOKESPECIAL edu/utd/sonnv/Test.toString ()Ljava/lang/String;
   L2
    ARETURN
    LOCALVARIABLE this Ledu/utd/sonnv/Test; L1 L2 0
   L3
    MAXSTACK = 1
    MAXLOCALS = 1
}
